Workbook

Sheet Indice
A1: ThinQQ — pasta de demonstração
A2: Rede Demo ThinQQ - Materiais de Construção (fictícia): 8 lojas em 5 regiões. Nenhuma empresa ou pessoa real; lojas, cidades e números são inventados (gerados por script).
A3: Clique no nome de um exemplo para ir ao gráfico; em cada exemplo, a célula A1 ("Voltar ao índice") traz você de volta. Os dados estão nas planilhas Dados, Lojas e Obras.
A4: Os gráficos são gráficos nativos do Excel e continuam ligados às tabelas: funcionam com ou sem o ThinQQ instalado. Setas, colchetes, marcas de corte e a escala do Gantt são recalculados só com o ThinQQ instalado; sem ele ficam como estão se os números mudarem.
A6: Nº | B6: Exemplo (clique para abrir) | C6: Tipo de gráfico | D6: Recursos em destaque | E6: Como criar no ThinQQ
A7: 1 | B7: Vendas 2025 por departamento e canal (colunas empilhadas, totais e rótulos) | C7: Colunas empilhadas | D7: Totais, Rótulos | E7: Inserir gráfico > Colunas > Colunas empilhadas (Totais e Rótulos já vêm ligados)
A8: 2 | B8: Vendas por loja, 2024 x 2025 (colunas agrupadas, espaço muito largo e delta entre barras) | C8: Colunas agrupadas | D8: Espaço (muito largo), Delta entre barras | E8: Inserir gráfico > Colunas > Colunas agrupadas; Gráfico selecionado > Espaço > Muito largo (120%); Setas > Delta clicando nas barras (clique na 1.ª e na última barra)
A9: 3 | B9: Mix de canais B2C/B2B por região (colunas 100% e indicador 100%) | C9: Colunas 100% | D9: Indicador 100% | E9: Inserir gráfico > Colunas > Colunas 100% (o Indicador 100% já vem ligado; Mais opções > Indicador 100% liga e desliga)
A10: 4 | B10: Vendas e custo mensais da loja Aurora Centro (nome no fim da linha) | C10: Linha | D10: Legenda: nome no fim da linha | E10: Inserir gráfico > Linha e área > Linha; Legenda > Nome no fim da linha
A11: 5 | B11: Da receita ao lucro em 2025 (cascata com conectores e seta de diferença) | C11: Cascata (colunas) | D11: Conectores, Seta diferença | E11: Inserir gráfico > Cascata > Cascata (colunas) (Conectores já vêm ligados); Setas > Seta diferença
A12: 6 | B12: Vendas 2025 por região e canal (barras empilhadas e seta de diferença) | C12: Barras empilhadas | D12: Seta diferença | E12: Inserir gráfico > Barras > Barras empilhadas; Setas > Seta diferença
A13: 7 | B13: Vendas por loja em R$ (barras agrupadas, rótulos em milhares) | C13: Barras agrupadas | D13: Formato (milhares) | E13: Inserir gráfico > Barras > Barras agrupadas; Formato > Milhares (1.234 → 1)
A14: 8 | B14: Mix de canais B2C/B2B por loja (barras 100%) | C14: Barras 100% | D14: — | E14: Inserir gráfico > Barras > Barras 100%
A15: 9 | B15: Da receita ao lucro em 2025 (cascata horizontal) | C15: Cascata (barras) | D15: — | E15: Inserir gráfico > Cascata > Cascata (barras)
A16: 10 | B16: Vendas trimestrais dos três maiores departamentos (área empilhada e linha de valor) | C16: Área empilhada | D16: Linha de valor (média) | E16: Inserir gráfico > Linha e área > Área empilhada; Mais opções > Linha de valor (média)
A17: 11 | B17: Participação trimestral dos três maiores departamentos (área 100%) | C17: Área 100% | D17: — | E17: Inserir gráfico > Linha e área > Área 100%
A18: 12 | B18: Vendas por canal e margem % da loja Aurora Centro (combinação com eixo secundário) | C18: Combinação (colunas + linha) | D18: Eixo secundário | E18: Inserir gráfico > Linha e área > Combinação (colunas + linha); Mais opções > Eixo secundário (linha)
... A34: 28 | B34: As duas maiores lojas: da receita ao lucro em 2025 (variação em valor) | C34: Cascata comparativa | D34: Variação em valor | E34: Inserir gráfico > Cascata > Cascata comparativa; Setas > Variação em valor; Legenda > Direita

Sheet Dados
A1: Loja | B1: Cidade | C1: Região | D1: Departamento | E1: Mês | F1: Vendas (R$) | G1: Custo (R$) | H1: Margem (R$) | I1: Unidades | J1: Ticket médio (R$) | K1: Vendas B2C (R$) | L1: Vendas B2B (R$)
A2: Aurora Centro | B2: Vila Aurora | C2: Sudeste | D2: Cimento e argamassa | E2: 45292 | F2: 520910 | G2: 414606 | H2: 106304 | I2: 14924 | J2: 447.07 | K2: 303105 | L2: 217805
A3: Aurora Centro | B3: Vila Aurora | C3: Sudeste | D3: Cimento e argamassa | E3: 45323 | F3: 488562 | G3: 393588 | H3: 94974 | I3: 14170 | J3: 426.02 | K3: 276755 | L3: 211807
A4: Aurora Centro | B4: Vila Aurora | C4: Sudeste | D4: Cimento e argamassa | E4: 45352 | F4: 488578 | G4: 392220 | H4: 96358 | I4: 14041 | J4: 435.8 | K4: 281920 | L4: 206658
A5: Aurora Centro | B5: Vila Aurora | C5: Sudeste | D5: Cimento e argamassa | E5: 45383 | F5: 516956 | G5: 413900 | H5: 103056 | I5: 15653 | J5: 459.98 | K5: 304981 | L5: 211975
A6: Aurora Centro | B6: Vila Aurora | C6: Sudeste | D6: Cimento e argamassa | E6: 45413 | F6: 539062 | G6: 433210 | H6: 105852 | I6: 15458 | J6: 463.36 | K6: 316205 | L6: 222857
A7: Aurora Centro | B7: Vila Aurora | C7: Sudeste | D7: Cimento e argamassa | E7: 45444 | F7: 562825 | G7: 444749 | H7: 118076 | I7: 16779 | J7: 450.2 | K7: 310216 | L7: 252609
A8: Aurora Centro | B8: Vila Aurora | C8: Sudeste | D8: Cimento e argamassa | E8: 45474 | F8: 599303 | G8: 477084 | H8: 122219 | I8: 18433 | J8: 428.01 | K8: 339960 | L8: 259343
A9: Aurora Centro | B9: Vila Aurora | C9: Sudeste | D9: Cimento e argamassa | E9: 45505 | F9: 571697 | G9: 448743 | H9: 122954 | I9: 16273 | J9: 463.81 | K9: 317597 | L9: 254100
A10: Aurora Centro | B10: Vila Aurora | C10: Sudeste | D10: Cimento e argamassa | E10: 45536 | F10: 608131 | G10: 482282 | H10: 125849 | I10: 18505 | J10: 462.96 | K10: 335220 | L10: 272911
A11: Aurora Centro | B11: Vila Aurora | C11: Sudeste | D11: Cimento e argamassa | E11: 45566 | F11: 612242 | G11: 489253 | H11: 122989 | I11: 17893 | J11: 437.84 | K11: 339052 | L11: 273190
A12: Aurora Centro | B12: Vila Aurora | C12: Sudeste | D12: Cimento e argamassa | E12: 45597 | F12: 599339 | G12: 478762 | H12: 120577 | I12: 16831 | J12: 426.94 | K12: 353491 | L12: 245848
A13: Aurora Centro | B13: Vila Aurora | C13: Sudeste | D13: Cimento e argamassa | E13: 45627 | F13: 629675 | G13: 506804 | H13: 122871 | I13: 18698 | J13: 450.67 | K13: 348530 | L13: 281145
... A1537: Rio Turquesa | B1537: Rio Turquesa | C1537: Norte | D1537: Ferragens | E1537: 45992 | F1537: 42746 | G1537: 23764 | H1537: 18982 | I1537: 4694 | J1537: 73.56 | K1537: 28228 | L1537: 14518

Sheet Lojas
A1: Loja | B1: Cidade | C1: Região | D1: Vendas 2025 (R$ mil) | E1: Meta 2026 (R$ mil) | F1: Inauguração
A2: Aurora Centro | B2: Vila Aurora | C2: Sudeste | D2: 26200 | E2: 28296 | F2: 39886
A3: Aurora Norte | B3: Vila Aurora | C3: Sudeste | D3: 16064 | E3: 17349 | F3: 42588
A4: Porto Sereno | B4: Porto Sereno | C4: Sul | D4: 21085 | E4: 22772 | F4: 40684
A5: Serra Clara | B5: Serra Clara | C5: Sul | D5: 13820 | E5: 14926 | F5: 43376
A6: Lago Prateado | B6: Lago Prateado | C6: Nordeste | D6: 14532 | E6: 15695 | F6: 41678
A7: Monte Alvorada | B7: Monte Alvorada | C7: Nordeste | D7: 10918 | E7: 11791 | F7: 44149
A8: Campo Dourado | B8: Campo Dourado | C8: Centro-Oeste | D8: 17656 | E8: 19068 | F8: 41482
A9: Rio Turquesa | B9: Rio Turquesa | C9: Norte | D9: 9435 | E9: 10190 | F9: 44660

Sheet Obras
A1: Obra | B1: Início | C1: Fim | D1: Plano
A2: Reforma da fachada (Aurora Centro) | B2: 46083 | C2: 46108 | D2: Reformas 2026
A3: Troca do telhado (Porto Sereno) | B3: 46097 | C3: 46136 | D3: Reformas 2026
A4: Novo depósito (Serra Clara) | B4: 46118 | C4: 46157 | D4: Reformas 2026
A5: Inauguração do depósito | B5: 46160 | D5: Reformas 2026
A6: Projeto e licenças | B6: 46027 | C6: 46108 | D6: Nova loja Vale do Ipê
A7: Obra civil | B7: 46118 | C7: 46374 | D7: Nova loja Vale do Ipê
A8: Instalações e acabamento | B8: 46391 | C8: 46507 | D8: Nova loja Vale do Ipê
A9: Montagem e estoque | B9: 46510 | C9: 46549 | D9: Nova loja Vale do Ipê
A10: Inauguração | B10: 46553 | D10: Nova loja Vale do Ipê

Sheet E01
A1: « Voltar ao índice
A2: 1) Vendas 2025 por departamento e canal (colunas empilhadas, totais e rótulos)
A3: O total de cada coluna fica acima dela e os rótulos dos segmentos acompanham as células. A tabela soma a planilha Dados (SOMASES): mude um valor em Dados e o gráfico muda junto.
A4: Como criar no ThinQQ: Inserir gráfico > Colunas > Colunas empilhadas (Totais e Rótulos já vêm ligados). Valores: R$ mil.
A6: Departamento | B6: B2C | C6: B2B
A7: Cimento e argamassa | B7: =ROUND(SUMIFS(Dados!$K:$K,Dados!$D:$D,$A7,Dados!$E:$E,">="&DATE(2025,1,1),Dados!$E:$E,"<"&DATE(2026,1,1))/1000,0) -> 29255 | C7: =ROUND(SUMIFS(Dados!$F:$F,Dados!$D:$D,$A7,Dados!$E:$E,">="&DATE(2025,1,1),Dados!$E:$E,"<"&DATE(2026,1,1))/1000,0)-$B7 -> 14069
A8: Pisos | B8: =ROUND(SUMIFS(Dados!$K:$K,Dados!$D:$D,$A8,Dados!$E:$E,">="&DATE(2025,1,1),Dados!$E:$E,"<"&DATE(2026,1,1))/1000,0) -> 15725 | C8: =ROUND(SUMIFS(Dados!$F:$F,Dados!$D:$D,$A8,Dados!$E:$E,">="&DATE(2025,1,1),Dados!$E:$E,"<"&DATE(2026,1,1))/1000,0)-$B8 -> 8045
A9: Tintas | B9: =ROUND(SUMIFS(Dados!$K:$K,Dados!$D:$D,$A9,Dados!$E:$E,">="&DATE(2025,1,1),Dados!$E:$E,"<"&DATE(2026,1,1))/1000,0) -> 10401 | C9: =ROUND(SUMIFS(Dados!$F:$F,Dados!$D:$D,$A9,Dados!$E:$E,">="&DATE(2025,1,1),Dados!$E:$E,"<"&DATE(2026,1,1))/1000,0)-$B9 -> 5301
A10: Hidráulica | B10: =ROUND(SUMIFS(Dados!$K:$K,Dados!$D:$D,$A10,Dados!$E:$E,">="&DATE(2025,1,1),Dados!$E:$E,"<"&DATE(2026,1,1))/1000,0) -> 8241 | C10: =ROUND(SUMIFS(Dados!$F:$F,Dados!$D:$D,$A10,Dados!$E:$E,">="&DATE(2025,1,1),Dados!$E:$E,"<"&DATE(2026,1,1))/1000,0)-$B10 -> 4076
A11: Elétrica | B11: =ROUND(SUMIFS(Dados!$K:$K,Dados!$D:$D,$A11,Dados!$E:$E,">="&DATE(2025,1,1),Dados!$E:$E,"<"&DATE(2026,1,1))/1000,0) -> 7705 | C11: =ROUND(SUMIFS(Dados!$F:$F,Dados!$D:$D,$A11,Dados!$E:$E,">="&DATE(2025,1,1),Dados!$E:$E,"<"&DATE(2026,1,1))/1000,0)-$B11 -> 3844
A12: Madeiras | B12: =ROUND(SUMIFS(Dados!$K:$K,Dados!$D:$D,$A12,Dados!$E:$E,">="&DATE(2025,1,1),Dados!$E:$E,"<"&DATE(2026,1,1))/1000,0) -> 6234 | C12: =ROUND(SUMIFS(Dados!$F:$F,Dados!$D:$D,$A12,Dados!$E:$E,">="&DATE(2025,1,1),Dados!$E:$E,"<"&DATE(2026,1,1))/1000,0)-$B12 -> 3016
A13: Ferramentas | B13: =ROUND(SUMIFS(Dados!$K:$K,Dados!$D:$D,$A13,Dados!$E:$E,">="&DATE(2025,1,1),Dados!$E:$E,"<"&DATE(2026,1,1))/1000,0) -> 5530 | C13: =ROUND(SUMIFS(Dados!$F:$F,Dados!$D:$D,$A13,Dados!$E:$E,">="&DATE(2025,1,1),Dados!$E:$E,"<"&DATE(2026,1,1))/1000,0)-$B13 -> 2780
A14: Ferragens | B14: =ROUND(SUMIFS(Dados!$K:$K,Dados!$D:$D,$A14,Dados!$E:$E,">="&DATE(2025,1,1),Dados!$E:$E,"<"&DATE(2026,1,1))/1000,0) -> 3696 | C14: =ROUND(SUMIFS(Dados!$F:$F,Dados!$D:$D,$A14,Dados!$E:$E,">="&DATE(2025,1,1),Dados!$E:$E,"<"&DATE(2026,1,1))/1000,0)-$B14 -> 1792

Sheet E02
A1: « Voltar ao índice
A2: 2) Vendas por loja, 2024 x 2025 (colunas agrupadas, espaço muito largo e delta entre barras)
A3: O espaço entre os grupos de colunas foi alargado para 120% (as agrupadas nascem com 80%). A seta no alto é um delta: ele compara duas barras quaisquer, aqui a de 2024 da primeira loja com a de 2025 da última (séries e lojas diferentes), e mostra a diferença em valor e em %. Os dois cliques nas barras escolhem as duas pontas; o delta é desenhado pelo ThinQQ e, sem ele instalado, fica como está se os números mudarem.
A4: Como criar no ThinQQ: Inserir gráfico > Colunas > Colunas agrupadas; Gráfico selecionado > Espaço > Muito largo (120%); Setas > Delta clicando nas barras (clique na 1.ª e na última barra). Valores: R$ milhões.
A6: Loja | B6: 2024 | C6: 2025
A7: Aurora Centro | B7: 23.3 | C7: 26.2
A8: Porto Sereno | B8: 18.5 | C8: 21.1
A9: Campo Dourado | B9: 16.2 | C9: 17.7
A10: Aurora Norte | B10: 14.8 | C10: 16.1
A11: Lago Prateado | B11: 13.4 | C11: 14.5
A12: Serra Clara | B12: 12.1 | C12: 13.8
A13: Monte Alvorada | B13: 10.2 | C13: 10.9
A14: Rio Turquesa | B14: 8.7 | C14: 9.4

Sheet E03
A1: « Voltar ao índice
A2: 3) Mix de canais B2C/B2B por região (colunas 100% e indicador 100%)
A3: Cada coluna é a participação de cada canal nas vendas da região; o indicador "100%" marca o topo comum das colunas.
A4: Como criar no ThinQQ: Inserir gráfico > Colunas > Colunas 100% (o Indicador 100% já vem ligado; Mais opções > Indicador 100% liga e desliga). Valores: R$ mil.
A6: Região | B6: B2C | C6: B2B
A7: Sudeste | B7: 25677 | C7: 16587
A8: Sul | B8: 23420 | C8: 11485
A9: Nordeste | B9: 19285 | C9: 6165
A10: Centro-Oeste | B10: 12171 | C10: 5485
A11: Norte | B11: 6236 | C11: 3199

Sheet E04
A1: « Voltar ao índice
A2: 4) Vendas e custo mensais da loja Aurora Centro (nome no fim da linha)
A3: Em vez da legenda, o nome de cada série aparece ao lado do último ponto da linha.
A4: Como criar no ThinQQ: Inserir gráfico > Linha e área > Linha; Legenda > Nome no fim da linha. Valores: R$ mil.
A6: Mês | B6: Vendas | C6: Custo
A7: 45658 | B7: 2072 | C7: 1420
A8: 45689 | B8: 1976 | C8: 1365
A9: 45717 | B9: 1903 | C9: 1308
A10: 45748 | B10: 1890 | C10: 1295
A11: 45778 | B11: 1950 | C11: 1347
A12: 45809 | B12: 2094 | C12: 1442
A13: 45839 | B13: 2248 | C13: 1546
A14: 45870 | B14: 2332 | C14: 1615
A15: 45901 | B15: 2372 | C15: 1620
A16: 45931 | B16: 2444 | C16: 1674
A17: 45962 | B17: 2467 | C17: 1692
A18: 45992 | B18: 2450 | C18: 1689

Sheet E05
A1: « Voltar ao índice
A2: 5) Da receita ao lucro em 2025 (cascata com conectores e seta de diferença)
A3: As linhas finas ligam o topo de cada degrau ao próximo. Na tabela, a letra "e" pede uma coluna de total calculada (EBITDA e Lucro). A seta à direita mostra a diferença entre o total da primeira barra (Receita) e o da última (Lucro), em valor e em %. A seta é desenhada pelo ThinQQ: sem ele instalado, fica como está se os números mudarem.
A4: Como criar no ThinQQ: Inserir gráfico > Cascata > Cascata (colunas) (Conectores já vêm ligados); Setas > Seta diferença. Valores: R$ mil.
A6: Etapa | B6: R$ mil
A7: Receita bruta | B7: 129710
A8: Custo das mercadorias | B8: -88293
A9: Despesas operacionais | B9: -27239
A10: EBITDA | B10: e
A11: Depreciação e juros | B11: -3243
A12: Impostos | B12: -3718
A13: Lucro líquido | B13: e

Sheet E06
A1: « Voltar ao índice
A2: 6) Vendas 2025 por região e canal (barras empilhadas e seta de diferença)
A3: A seta mostra a diferença entre o total da primeira e o da última região da tabela.
A4: Como criar no ThinQQ: Inserir gráfico > Barras > Barras empilhadas; Setas > Seta diferença. Valores: R$ mil.
A6: Região | B6: B2C | C6: B2B
A7: Sudeste | B7: 25677 | C7: 16587
A8: Sul | B8: 23420 | C8: 11485
A9: Nordeste | B9: 19285 | C9: 6165
A10: Centro-Oeste | B10: 12171 | C10: 5485
A11: Norte | B11: 6236 | C11: 3199

Sheet E07
A1: « Voltar ao índice
A2: 7) Vendas por loja em R$ (barras agrupadas, rótulos em milhares)
A3: A tabela está em reais; o formato "Milhares" mostra os rótulos em R$ mil sem mudar os números da tabela.
A4: Como criar no ThinQQ: Inserir gráfico > Barras > Barras agrupadas; Formato > Milhares (1.234 → 1). Valores: R$ na tabela, rótulos em R$ mil.
A6: Loja | B6: 2024 | C6: 2025
A7: Aurora Centro | B7: 23323828 | C7: 26200229
A8: Porto Sereno | B8: 18479885 | C8: 21085258
A9: Campo Dourado | B9: 16236776 | C9: 17656275
A10: Aurora Norte | B10: 14773252 | C10: 16064115
A11: Lago Prateado | B11: 13402182 | C11: 14531945
A12: Serra Clara | B12: 12087322 | C12: 13819600
A13: Monte Alvorada | B13: 10205303 | C13: 10917761
A14: Rio Turquesa | B14: 8715402 | C14: 9435053

Sheet E08
A1: « Voltar ao índice
A2: 8) Mix de canais B2C/B2B por loja (barras 100%)
A3: Participação de cada canal nas vendas de 2025 de cada loja.
A4: Como criar no ThinQQ: Inserir gráfico > Barras > Barras 100%. Valores: R$ mil.
A6: Loja | B6: B2C | C6: B2B
A7: Aurora Centro | B7: 14929 | C7: 11271
A8: Porto Sereno | B8: 16058 | C8: 5027
A9: Campo Dourado | B9: 12171 | C9: 5485
A10: Aurora Norte | B10: 10747 | C10: 5317
A11: Lago Prateado | B11: 11461 | C11: 3071
A12: Serra Clara | B12: 7362 | C12: 6458
A13: Monte Alvorada | B13: 7824 | C13: 3094
A14: Rio Turquesa | B14: 6236 | C14: 3199

Sheet E09
A1: « Voltar ao índice
A2: 9) Da receita ao lucro em 2025 (cascata horizontal)
A3: A mesma ponte do exemplo 5, na horizontal: os nomes das etapas ficam legíveis à esquerda.
A4: Como criar no ThinQQ: Inserir gráfico > Cascata > Cascata (barras). Valores: R$ mil.
A6: Etapa | B6: R$ mil
A7: Receita bruta | B7: 129710
A8: Custo das mercadorias | B8: -88293
A9: Despesas operacionais | B9: -27239
A10: EBITDA | B10: e
A11: Depreciação e juros | B11: -3243
A12: Impostos | B12: -3718
A13: Lucro líquido | B13: e

Sheet E10
A1: « Voltar ao índice
A2: 10) Vendas trimestrais dos três maiores departamentos (área empilhada e linha de valor)
A3: A linha tracejada marca a média dos totais trimestrais, com o valor no rótulo à direita.
A4: Como criar no ThinQQ: Inserir gráfico > Linha e área > Área empilhada; Mais opções > Linha de valor (média). Valores: R$ mil.
A6: Trimestre | B6: Tintas | C6: Pisos | D6: Cimento e argamassa
A7: T1/24 | B7: 3224 | C7: 4499 | D7: 9316
A8: T2/24 | B8: 3217 | C8: 4526 | D8: 9211
A9: T3/24 | B9: 3746 | C9: 5356 | D9: 10495
A10: T4/24 | B10: 3943 | C10: 5792 | D10: 11163
A11: T1/25 | B11: 3588 | C11: 5306 | D11: 9955
A12: T2/25 | B12: 3538 | C12: 5367 | D12: 10054
A13: T3/25 | B13: 4162 | C13: 6298 | D13: 11350
A14: T4/25 | B14: 4415 | C14: 6800 | D14: 11965

Sheet E11
A1: « Voltar ao índice
A2: 11) Participação trimestral dos três maiores departamentos (área 100%)
A3: A mesma tabela do exemplo 10, em participação de cada departamento no total do trimestre: pisos ganham espaço.
A4: Como criar no ThinQQ: Inserir gráfico > Linha e área > Área 100%. Valores: R$ mil.
A6: Trimestre | B6: Tintas | C6: Pisos | D6: Cimento e argamassa
A7: T1/24 | B7: 3224 | C7: 4499 | D7: 9316
A8: T2/24 | B8: 3217 | C8: 4526 | D8: 9211
A9: T3/24 | B9: 3746 | C9: 5356 | D9: 10495
A10: T4/24 | B10: 3943 | C10: 5792 | D10: 11163
A11: T1/25 | B11: 3588 | C11: 5306 | D11: 9955
A12: T2/25 | B12: 3538 | C12: 5367 | D12: 10054
A13: T3/25 | B13: 4162 | C13: 6298 | D13: 11350
A14: T4/25 | B14: 4415 | C14: 6800 | D14: 11965

Sheet E12
A1: « Voltar ao índice
A2: 12) Vendas por canal e margem % da loja Aurora Centro (combinação com eixo secundário)
A3: A linha da margem % (última coluna da tabela) tem a sua própria escala, à direita, num eixo secundário que liga sozinho quando as grandezas diferem muito; o estilo ThinQQ esconde os eixos de valores, o secundário também. Com os totais das colunas ligados, a linha fica numa faixa acima deles.
A4: Como criar no ThinQQ: Inserir gráfico > Linha e área > Combinação (colunas + linha); Mais opções > Eixo secundário (linha). Valores: R$ mil.
A6: Mês | B6: B2C | C6: B2B | D6: Margem %
A7: 45658 | B7: 1171 | C7: 901 | D7: 0.315
A8: 45689 | B8: 1142 | C8: 834 | D8: 0.309
A9: 45717 | B9: 1080 | C9: 823 | D9: 0.313
A10: 45748 | B10: 1083 | C10: 807 | D10: 0.315
A11: 45778 | B11: 1105 | C11: 845 | D11: 0.309
A12: 45809 | B12: 1184 | C12: 910 | D12: 0.312
A13: 45839 | B13: 1278 | C13: 970 | D13: 0.312
A14: 45870 | B14: 1311 | C14: 1021 | D14: 0.308
A15: 45901 | B15: 1369 | C15: 1003 | D15: 0.317
A16: 45931 | B16: 1404 | C16: 1040 | D16: 0.315
A17: 45962 | B17: 1420 | C17: 1047 | D17: 0.314
A18: 45992 | B18: 1381 | C18: 1069 | D18: 0.311

Sheet E13
A1: « Voltar ao índice
A2: 13) Regiões x grupos de produto em 2025 (Mekko %)
A3: A largura de cada coluna é o peso da região nas vendas; a altura de cada faixa é a participação do grupo de produto na região.
A4: Como criar no ThinQQ: Inserir gráfico > Mais tipos > Mekko (%). Valores: R$ mil.
A6: Região | B6: Construção | C6: Acabamento | D6: Instalações
A7: Sudeste | B7: 16128 | C7: 15176 | D7: 10960
A8: Sul | B8: 14703 | C8: 11116 | D8: 9086
A9: Nordeste | B9: 13144 | C9: 6289 | D9: 6017
A10: Centro-Oeste | B10: 8781 | C10: 4873 | D10: 4002
A11: Norte | B11: 5306 | C11: 2018 | D11: 2111

Sheet E14
A1: « Voltar ao índice
A2: 14) Regiões x grupos, largura = nº de lojas (Mekko em unidades)
A3: A largura é o número de lojas da região (coluna Lojas) e a altura são as vendas médias por loja em 2025: a área de cada bloco é a venda total do grupo na região.
A4: Como criar no ThinQQ: Inserir gráfico > Mais tipos > Mekko (unidades). Valores: R$ mil.
A6: Região | B6: Lojas | C6: Construção | D6: Acabamento | E6: Instalações
A7: Sudeste | B7: 2 | C7: 8064 | D7: 7588 | E7: 5480
A8: Sul | B8: 2 | C8: 7352 | D8: 5558 | E8: 4543
A9: Nordeste | B9: 2 | C9: 6572 | D9: 3145 | E9: 3008
A10: Centro-Oeste | B10: 1 | C10: 8781 | D10: 4873 | E10: 4002
A11: Norte | B11: 1 | C11: 5306 | D11: 2018 | E11: 2111

Sheet E15
A1: « Voltar ao índice
A2: 15) Reformas de março a maio (Gantt em semanas, com colchete)
A3: Cronograma curto: a escala do tempo fica em semanas. O colchete agrupa as duas primeiras obras; a linha sem data de fim vira um marco.
A4: Como criar no ThinQQ: Inserir gráfico > Mais tipos > Gantt; Setas > Colchete (Gantt).
A6: Obra | B6: Início | C6: Fim
A7: Reforma da fachada (Aurora Centro) | B7: 46083 | C7: 46108
A8: Troca do telhado (Porto Sereno) | B8: 46097 | C8: 46136
A9: Novo depósito (Serra Clara) | B9: 46118 | C9: 46157
A10: Inauguração do depósito | B10: 46160

Sheet E16
A1: « Voltar ao índice
A2: 16) Plano de abertura de uma nova loja (Gantt em meses)
A3: Cronograma de 18 meses: a escala do tempo passa a meses sozinha. A inauguração (sem data de fim) é um marco.
A4: Como criar no ThinQQ: Inserir gráfico > Mais tipos > Gantt.
A6: Etapa | B6: Início | C6: Fim
A7: Projeto e licenças | B7: 46027 | C7: 46108
A8: Obra civil | B8: 46118 | C8: 46374
A9: Instalações e acabamento | B9: 46391 | C9: 46507
A10: Montagem e estoque | B10: 46510 | C10: 46549
A11: Inauguração | B11: 46553

Sheet E17
A1: « Voltar ao índice
A2: 17) Vendas 2025 por região (pizza, rótulos fora)
A3: O nome e o valor de cada fatia ficam fora da pizza, legíveis mesmo na fatia pequena (Norte).
A4: Como criar no ThinQQ: Inserir gráfico > Mais tipos > Pizza; Mais opções > Rótulos fora da pizza. Valores: R$ mil.
A6: Região | B6: Vendas 2025
A7: Sudeste | B7: 42264
A8: Sul | B8: 34905
A9: Nordeste | B9: 25450
A10: Centro-Oeste | B10: 17656
A11: Norte | B11: 9435

Sheet E18
A1: « Voltar ao índice
A2: 18) Vendas 2025 por região (rosca, paleta em tons de cinza)
A3: A paleta "Tons de cinza" troca as cores de todas as séries de uma vez (útil para impressão).
A4: Como criar no ThinQQ: Inserir gráfico > Mais tipos > Rosca; Paleta > Tons de cinza. Valores: R$ mil.
A6: Região | B6: Vendas 2025
A7: Sudeste | B7: 42264
A8: Sul | B8: 34905
A9: Nordeste | B9: 25450
A10: Centro-Oeste | B10: 17656
A11: Norte | B11: 9435

Sheet E19
A1: « Voltar ao índice
A2: 19) Vendas B2C x B2B por loja (borboleta)
A3: B2C à esquerda e B2B à direita, com os nomes das lojas no centro e o total de cada loja à direita.
A4: Como criar no ThinQQ: Inserir gráfico > Mais tipos > Borboleta. Valores: R$ mil.
A6: Loja | B6: B2C | C6: B2B
A7: Aurora Centro | B7: 14929 | C7: 11271
A8: Porto Sereno | B8: 16058 | C8: 5027
A9: Campo Dourado | B9: 12171 | C9: 5485
A10: Aurora Norte | B10: 10747 | C10: 5317
A11: Lago Prateado | B11: 11461 | C11: 3071
A12: Serra Clara | B12: 7362 | C12: 6458
A13: Monte Alvorada | B13: 7824 | C13: 3094
A14: Rio Turquesa | B14: 6236 | C14: 3199

Sheet E20
A1: « Voltar ao índice
A2: 20) Ticket médio x margem por loja (dispersão, tendência e quadrantes)
A3: Lojas com mais vendas para empresas (B2B) têm ticket maior e margem menor: a tendência tracejada mostra a relação e os eixos cruzam nas médias, formando quadrantes.
A4: Como criar no ThinQQ: Inserir gráfico > Mais tipos > Dispersão; Mais opções > Linha de tendência e Quadrantes (médias). Valores: ticket em R$, margem bruta em %.
A6: Loja | B6: Ticket médio (R$) | C6: Margem bruta
A7: Aurora Centro | B7: 286 | C7: 0.312
A8: Porto Sereno | B8: 252 | C8: 0.331
A9: Campo Dourado | B9: 269 | C9: 0.32
A10: Aurora Norte | B10: 274 | C10: 0.326
A11: Lago Prateado | B11: 244 | C11: 0.332
A12: Serra Clara | B12: 283 | C12: 0.301
A13: Monte Alvorada | B13: 257 | C13: 0.319
A14: Rio Turquesa | B14: 259 | C14: 0.306

Sheet E21
A1: « Voltar ao índice
A2: 21) Ticket x margem x vendas por departamento (bolhas)
A3: Cada bolha é um departamento: posição = ticket médio e margem, área = vendas de 2025, cor = grupo de produto.
A4: Como criar no ThinQQ: Inserir gráfico > Mais tipos > Bolhas. Valores: ticket em R$, margem bruta em %, vendas em R$ mil.
A6: Departamento | B6: Ticket médio (R$) | C6: Margem bruta | D6: Vendas 2025 | E6: Grupo
A7: Cimento e argamassa | B7: 418 | C7: 0.221 | D7: 43324 | E7: Construção
A8: Pisos | B8: 696 | C8: 0.338 | D8: 23770 | E8: Acabamento
A9: Tintas | B9: 361 | C9: 0.381 | D9: 15702 | E9: Acabamento
A10: Hidráulica | B10: 210 | C10: 0.358 | D10: 12317 | E10: Instalações
A11: Elétrica | B11: 120 | C11: 0.4 | D11: 11549 | E11: Instalações
A12: Madeiras | B12: 377 | C12: 0.291 | D12: 9250 | E12: Construção
A13: Ferramentas | B13: 160 | C13: 0.429 | D13: 8310 | E13: Instalações
A14: Ferragens | B14: 74 | C14: 0.461 | D14: 5488 | E14: Construção

Sheet E22
A1: « Voltar ao índice
A2: 22) Crescimento 2024-2025 de três departamentos (seta CAGR)
A3: A seta mostra a taxa de crescimento anual composta entre os totais das duas colunas. A seta é desenhada pelo ThinQQ: sem ele, continua onde está se os números mudarem.
A4: Como criar no ThinQQ: Inserir gráfico > Colunas > Colunas empilhadas; Setas > Seta CAGR. Valores: R$ mil.
A6: Ano | B6: Cimento e argamassa | C6: Pisos | D6: Tintas
A7: 2024 | B7: 40185 | C7: 20173 | D7: 14131
A8: 2025 | B8: 43324 | C8: 23770 | D8: 15702

Sheet E23
A1: « Voltar ao índice
A2: 23) Participações que somam 100% (soma consistente no gráfico e na tabela)
A3: Os rótulos de cada coluna somam exatamente 100%; compare com o exemplo 13, a mesma tabela sem a soma consistente, onde Nordeste e Centro-Oeste somam 101% e Norte 99%. Abaixo, "Arredondar intervalo" grava fórmulas que fazem o mesmo numa tabela comum (compare com o arredondamento simples).
A4: Como criar no ThinQQ: Inserir gráfico > Colunas > Colunas 100%; Mais opções > Rótulos com soma consistente; Mais opções > Arredondar intervalo... Valores: R$ mil e participações.
A6: Região | B6: Construção | C6: Acabamento | D6: Instalações
A7: Sudeste | B7: 16128 | C7: 15176 | D7: 10960
A8: Sul | B8: 14703 | C8: 11116 | D8: 9086
A9: Nordeste | B9: 13144 | C9: 6289 | D9: 6017
A10: Centro-Oeste | B10: 8781 | C10: 4873 | D10: 4002
A11: Norte | B11: 5306 | C11: 2018 | D11: 2111
A14: Arredondar intervalo: loja Campo Dourado, vendas 2025
A15: Departamento | B15: Exata | C15: Arredondamento simples | D15: Soma consistente
A16: Cimento e argamassa | B16: 0.37246854 | C16: =ROUND(B16,2) -> 0.37 | D16: =ROUND('E23'!$B$16,(2))+POWER(10,-(2))*(IF(ROUND((ROUND(SUM('E23'!$B$16:$B$23),(2))-SUMPRODUCT(ROUND('E23'!$B$16:$B$23,(2))))/POWER(10,-(2)),0)>0,--((SUMPRODUCT(--(ROUND(('E23'!$B$16:$B$23-ROUND('E23'!$B$16:$B$23,(2)))/POWER(10,-(2)),9)>ROUND(('E23'!$B$16-ROUND('E23'!$B$16,(2)))/POWER(10,-(2)),9)))+SUMPRODUCT(--(ROUND(('E23'!$B$16-ROUND('E23'!$B$16,(2)))/POWER(10,-(2)),9)=ROUND(('E23'!$B$16-ROUND('E23'!$B$16,(2)))/POWER(10,-(2)),9))))<=ROUND((ROUND(SUM('E23'!$B$16:$B$23),(2))-SUMPRODUCT(ROUND('E23'!$B$16:$B$23,(2))))/POWER(10,-(2)),0)),0)-IF(ROUND((ROUND(SUM('E23'!$B$16:$B$23),(2))-SUMPRODUCT(ROUND('E23'!$B$16:$B$23,(2))))/POWER(10,-(2)),0)<0,--((SUMPRODUCT(--(ROUND(('E23'!$B$16:$B$23-ROUND('E23'!$B$16:$B$23,(2)))/POWER(10,-(2)),9)<ROUND(('E23'!$B$16-ROUND('E23'!$B$16,(2)))/POWER(10,-(2)),9)))+SUMPRODUCT(--(ROUND(('E23'!$B$16-ROUND('E23'!$B$16,(2)))/POWER(10,-(2)),9)=ROUND(('E23'!$B$16-ROUND('E23'!$B$16,(2)))/POWER(10,-(2)),9))))<=-ROUND((ROUND(SUM('E23'!$B$16:$B$23),(2))-SUMPRODUCT(ROUND('E23'!$B$16:$B$23,(2))))/POWER(10,-(2)),0)),0)) -> 0.37
A17: Pisos | B17: 0.1665882 | C17: =ROUND(B17,2) -> 0.17 | D17: =ROUND('E23'!$B$17,(2))+POWER(10,-(2))*(IF(ROUND((ROUND(SUM('E23'!$B$16:$B$23),(2))-SUMPRODUCT(ROUND('E23'!$B$16:$B$23,(2))))/POWER(10,-(2)),0)>0,--((SUMPRODUCT(--(ROUND(('E23'!$B$16:$B$23-ROUND('E23'!$B$16:$B$23,(2)))/POWER(10,-(2)),9)>ROUND(('E23'!$B$17-ROUND('E23'!$B$17,(2)))/POWER(10,-(2)),9)))+SUMPRODUCT(--(ROUND(('E23'!$B$16:$B$17-ROUND('E23'!$B$16:$B$17,(2)))/POWER(10,-(2)),9)=ROUND(('E23'!$B$17-ROUND('E23'!$B$17,(2)))/POWER(10,-(2)),9))))<=ROUND((ROUND(SUM('E23'!$B$16:$B$23),(2))-SUMPRODUCT(ROUND('E23'!$B$16:$B$23,(2))))/POWER(10,-(2)),0)),0)-IF(ROUND((ROUND(SUM('E23'!$B$16:$B$23),(2))-SUMPRODUCT(ROUND('E23'!$B$16:$B$23,(2))))/POWER(10,-(2)),0)<0,--((SUMPRODUCT(--(ROUND(('E23'!$B$16:$B$23-ROUND('E23'!$B$16:$B$23,(2)))/POWER(10,-(2)),9)<ROUND(('E23'!$B$17-ROUND('E23'!$B$17,(2)))/POWER(10,-(2)),9)))+SUMPRODUCT(--(ROUND(('E23'!$B$16:$B$17-ROUND('E23'!$B$16:$B$17,(2)))/POWER(10,-(2)),9)=ROUND(('E23'!$B$17-ROUND('E23'!$B$17,(2)))/POWER(10,-(2)),9))))<=-ROUND((ROUND(SUM('E23'!$B$16:$B$23),(2))-SUMPRODUCT(ROUND('E23'!$B$16:$B$23,(2))))/POWER(10,-(2)),0)),0)) -> 0.17
A18: Tintas | B18: 0.10943056 | C18: =ROUND(B18,2) -> 0.11 | D18: =ROUND('E23'!$B$18,(2))+POWER(10,-(2))*(IF(ROUND((ROUND(SUM('E23'!$B$16:$B$23),(2))-SUMPRODUCT(ROUND('E23'!$B$16:$B$23,(2))))/POWER(10,-(2)),0)>0,--((SUMPRODUCT(--(ROUND(('E23'!$B$16:$B$23-ROUND('E23'!$B$16:$B$23,(2)))/POWER(10,-(2)),9)>ROUND(('E23'!$B$18-ROUND('E23'!$B$18,(2)))/POWER(10,-(2)),9)))+SUMPRODUCT(--(ROUND(('E23'!$B$16:$B$18-ROUND('E23'!$B$16:$B$18,(2)))/POWER(10,-(2)),9)=ROUND(('E23'!$B$18-ROUND('E23'!$B$18,(2)))/POWER(10,-(2)),9))))<=ROUND((ROUND(SUM('E23'!$B$16:$B$23),(2))-SUMPRODUCT(ROUND('E23'!$B$16:$B$23,(2))))/POWER(10,-(2)),0)),0)-IF(ROUND((ROUND(SUM('E23'!$B$16:$B$23),(2))-SUMPRODUCT(ROUND('E23'!$B$16:$B$23,(2))))/POWER(10,-(2)),0)<0,--((SUMPRODUCT(--(ROUND(('E23'!$B$16:$B$23-ROUND('E23'!$B$16:$B$23,(2)))/POWER(10,-(2)),9)<ROUND(('E23'!$B$18-ROUND('E23'!$B$18,(2)))/POWER(10,-(2)),9)))+SUMPRODUCT(--(ROUND(('E23'!$B$16:$B$18-ROUND('E23'!$B$16:$B$18,(2)))/POWER(10,-(2)),9)=ROUND(('E23'!$B$18-ROUND('E23'!$B$18,(2)))/POWER(10,-(2)),9))))<=-ROUND((ROUND(SUM('E23'!$B$16:$B$23),(2))-SUMPRODUCT(ROUND('E23'!$B$16:$B$23,(2))))/POWER(10,-(2)),0)),0)) -> 0.11
A19: Hidráulica | B19: 0.08610191 | C19: =ROUND(B19,2) -> 0.09 | D19: =ROUND('E23'!$B$19,(2))+POWER(10,-(2))*(IF(ROUND((ROUND(SUM('E23'!$B$16:$B$23),(2))-SUMPRODUCT(ROUND('E23'!$B$16:$B$23,(2))))/POWER(10,-(2)),0)>0,--((SUMPRODUCT(--(ROUND(('E23'!$B$16:$B$23-ROUND('E23'!$B$16:$B$23,(2)))/POWER(10,-(2)),9)>ROUND(('E23'!$B$19-ROUND('E23'!$B$19,(2)))/POWER(10,-(2)),9)))+SUMPRODUCT(--(ROUND(('E23'!$B$16:$B$19-ROUND('E23'!$B$16:$B$19,(2)))/POWER(10,-(2)),9)=ROUND(('E23'!$B$19-ROUND('E23'!$B$19,(2)))/POWER(10,-(2)),9))))<=ROUND((ROUND(SUM('E23'!$B$16:$B$23),(2))-SUMPRODUCT(ROUND('E23'!$B$16:$B$23,(2))))/POWER(10,-(2)),0)),0)-IF(ROUND((ROUND(SUM('E23'!$B$16:$B$23),(2))-SUMPRODUCT(ROUND('E23'!$B$16:$B$23,(2))))/POWER(10,-(2)),0)<0,--((SUMPRODUCT(--(ROUND(('E23'!$B$16:$B$23-ROUND('E23'!$B$16:$B$23,(2)))/POWER(10,-(2)),9)<ROUND(('E23'!$B$19-ROUND('E23'!$B$19,(2)))/POWER(10,-(2)),9)))+SUMPRODUCT(--(ROUND(('E23'!$B$16:$B$19-ROUND('E23'!$B$16:$B$19,(2)))/POWER(10,-(2)),9)=ROUND(('E23'!$B$19-ROUND('E23'!$B$19,(2)))/POWER(10,-(2)),9))))<=-ROUND((ROUND(SUM('E23'!$B$16:$B$23),(2))-SUMPRODUCT(ROUND('E23'!$B$16:$B$23,(2))))/POWER(10,-(2)),0)),0)) -> 0.08
A20: Elétrica | B20: 0.081516062 | C20: =ROUND(B20,2) -> 0.08 | D20: =ROUND('E23'!$B$20,(2))+POWER(10,-(2))*(IF(ROUND((ROUND(SUM('E23'!$B$16:$B$23),(2))-SUMPRODUCT(ROUND('E23'!$B$16:$B$23,(2))))/POWER(10,-(2)),0)>0,--((SUMPRODUCT(--(ROUND(('E23'!$B$16:$B$23-ROUND('E23'!$B$16:$B$23,(2)))/POWER(10,-(2)),9)>ROUND(('E23'!$B$20-ROUND('E23'!$B$20,(2)))/POWER(10,-(2)),9)))+SUMPRODUCT(--(ROUND(('E23'!$B$16:$B$20-ROUND('E23'!$B$16:$B$20,(2)))/POWER(10,-(2)),9)=ROUND(('E23'!$B$20-ROUND('E23'!$B$20,(2)))/POWER(10,-(2)),9))))<=ROUND((ROUND(SUM('E23'!$B$16:$B$23),(2))-SUMPRODUCT(ROUND('E23'!$B$16:$B$23,(2))))/POWER(10,-(2)),0)),0)-IF(ROUND((ROUND(SUM('E23'!$B$16:$B$23),(2))-SUMPRODUCT(ROUND('E23'!$B$16:$B$23,(2))))/POWER(10,-(2)),0)<0,--((SUMPRODUCT(--(ROUND(('E23'!$B$16:$B$23-ROUND('E23'!$B$16:$B$23,(2)))/POWER(10,-(2)),9)<ROUND(('E23'!$B$20-ROUND('E23'!$B$20,(2)))/POWER(10,-(2)),9)))+SUMPRODUCT(--(ROUND(('E23'!$B$16:$B$20-ROUND('E23'!$B$16:$B$20,(2)))/POWER(10,-(2)),9)=ROUND(('E23'!$B$20-ROUND('E23'!$B$20,(2)))/POWER(10,-(2)),9))))<=-ROUND((ROUND(SUM('E23'!$B$16:$B$23),(2))-SUMPRODUCT(ROUND('E23'!$B$16:$B$23,(2))))/POWER(10,-(2)),0)),0)) -> 0.08
A21: Madeiras | B21: 0.077419784 | C21: =ROUND(B21,2) -> 0.08 | D21: =ROUND('E23'!$B$21,(2))+POWER(10,-(2))*(IF(ROUND((ROUND(SUM('E23'!$B$16:$B$23),(2))-SUMPRODUCT(ROUND('E23'!$B$16:$B$23,(2))))/POWER(10,-(2)),0)>0,--((SUMPRODUCT(--(ROUND(('E23'!$B$16:$B$23-ROUND('E23'!$B$16:$B$23,(2)))/POWER(10,-(2)),9)>ROUND(('E23'!$B$21-ROUND('E23'!$B$21,(2)))/POWER(10,-(2)),9)))+SUMPRODUCT(--(ROUND(('E23'!$B$16:$B$21-ROUND('E23'!$B$16:$B$21,(2)))/POWER(10,-(2)),9)=ROUND(('E23'!$B$21-ROUND('E23'!$B$21,(2)))/POWER(10,-(2)),9))))<=ROUND((ROUND(SUM('E23'!$B$16:$B$23),(2))-SUMPRODUCT(ROUND('E23'!$B$16:$B$23,(2))))/POWER(10,-(2)),0)),0)-IF(ROUND((ROUND(SUM('E23'!$B$16:$B$23),(2))-SUMPRODUCT(ROUND('E23'!$B$16:$B$23,(2))))/POWER(10,-(2)),0)<0,--((SUMPRODUCT(--(ROUND(('E23'!$B$16:$B$23-ROUND('E23'!$B$16:$B$23,(2)))/POWER(10,-(2)),9)<ROUND(('E23'!$B$21-ROUND('E23'!$B$21,(2)))/POWER(10,-(2)),9)))+SUMPRODUCT(--(ROUND(('E23'!$B$16:$B$21-ROUND('E23'!$B$16:$B$21,(2)))/POWER(10,-(2)),9)=ROUND(('E23'!$B$21-ROUND('E23'!$B$21,(2)))/POWER(10,-(2)),9))))<=-ROUND((ROUND(SUM('E23'!$B$16:$B$23),(2))-SUMPRODUCT(ROUND('E23'!$B$16:$B$23,(2))))/POWER(10,-(2)),0)),0)) -> 0.08
A22: Ferramentas | B22: 0.059054472 | C22: =ROUND(B22,2) -> 0.06 | D22: =ROUND('E23'!$B$22,(2))+POWER(10,-(2))*(IF(ROUND((ROUND(SUM('E23'!$B$16:$B$23),(2))-SUMPRODUCT(ROUND('E23'!$B$16:$B$23,(2))))/POWER(10,-(2)),0)>0,--((SUMPRODUCT(--(ROUND(('E23'!$B$16:$B$23-ROUND('E23'!$B$16:$B$23,(2)))/POWER(10,-(2)),9)>ROUND(('E23'!$B$22-ROUND('E23'!$B$22,(2)))/POWER(10,-(2)),9)))+SUMPRODUCT(--(ROUND(('E23'!$B$16:$B$22-ROUND('E23'!$B$16:$B$22,(2)))/POWER(10,-(2)),9)=ROUND(('E23'!$B$22-ROUND('E23'!$B$22,(2)))/POWER(10,-(2)),9))))<=ROUND((ROUND(SUM('E23'!$B$16:$B$23),(2))-SUMPRODUCT(ROUND('E23'!$B$16:$B$23,(2))))/POWER(10,-(2)),0)),0)-IF(ROUND((ROUND(SUM('E23'!$B$16:$B$23),(2))-SUMPRODUCT(ROUND('E23'!$B$16:$B$23,(2))))/POWER(10,-(2)),0)<0,--((SUMPRODUCT(--(ROUND(('E23'!$B$16:$B$23-ROUND('E23'!$B$16:$B$23,(2)))/POWER(10,-(2)),9)<ROUND(('E23'!$B$22-ROUND('E23'!$B$22,(2)))/POWER(10,-(2)),9)))+SUMPRODUCT(--(ROUND(('E23'!$B$16:$B$22-ROUND('E23'!$B$16:$B$22,(2)))/POWER(10,-(2)),9)=ROUND(('E23'!$B$22-ROUND('E23'!$B$22,(2)))/POWER(10,-(2)),9))))<=-ROUND((ROUND(SUM('E23'!$B$16:$B$23),(2))-SUMPRODUCT(ROUND('E23'!$B$16:$B$23,(2))))/POWER(10,-(2)),0)),0)) -> 0.06
A23: Ferragens | B23: 0.047420478 | C23: =ROUND(B23,2) -> 0.05 | D23: =ROUND('E23'!$B$23,(2))+POWER(10,-(2))*(IF(ROUND((ROUND(SUM('E23'!$B$16:$B$23),(2))-SUMPRODUCT(ROUND('E23'!$B$16:$B$23,(2))))/POWER(10,-(2)),0)>0,--((SUMPRODUCT(--(ROUND(('E23'!$B$16:$B$23-ROUND('E23'!$B$16:$B$23,(2)))/POWER(10,-(2)),9)>ROUND(('E23'!$B$23-ROUND('E23'!$B$23,(2)))/POWER(10,-(2)),9)))+SUMPRODUCT(--(ROUND(('E23'!$B$16:$B$23-ROUND('E23'!$B$16:$B$23,(2)))/POWER(10,-(2)),9)=ROUND(('E23'!$B$23-ROUND('E23'!$B$23,(2)))/POWER(10,-(2)),9))))<=ROUND((ROUND(SUM('E23'!$B$16:$B$23),(2))-SUMPRODUCT(ROUND('E23'!$B$16:$B$23,(2))))/POWER(10,-(2)),0)),0)-IF(ROUND((ROUND(SUM('E23'!$B$16:$B$23),(2))-SUMPRODUCT(ROUND('E23'!$B$16:$B$23,(2))))/POWER(10,-(2)),0)<0,--((SUMPRODUCT(--(ROUND(('E23'!$B$16:$B$23-ROUND('E23'!$B$16:$B$23,(2)))/POWER(10,-(2)),9)<ROUND(('E23'!$B$23-ROUND('E23'!$B$23,(2)))/POWER(10,-(2)),9)))+SUMPRODUCT(--(ROUND(('E23'!$B$16:$B$23-ROUND('E23'!$B$16:$B$23,(2)))/POWER(10,-(2)),9)=ROUND(('E23'!$B$23-ROUND('E23'!$B$23,(2)))/POWER(10,-(2)),9))))<=-ROUND((ROUND(SUM('E23'!$B$16:$B$23),(2))-SUMPRODUCT(ROUND('E23'!$B$16:$B$23,(2))))/POWER(10,-(2)),0)),0)) -> 0.05
A24: Total | B24: =SUM(B16:B23) -> 1 | C24: =SUM(C16:C23) -> 1.01 | D24: =SUM(D16:D23) -> 1

Sheet E24
A1: « Voltar ao índice
A2: 24) Cimento e argamassa dominam as vendas: corte de eixo
A3: A mesma tabela do exemplo 1: a coluna muito maior é cortada (marca de corte) e o total real continua no rótulo; as demais colunas ganham altura para comparação.
A4: Como criar no ThinQQ: Inserir gráfico > Colunas > Colunas empilhadas; Mais opções > Corte de eixo... Valores: R$ mil.
A6: Departamento | B6: B2C | C6: B2B
A7: Cimento e argamassa | B7: 29255 | C7: 14069
A8: Pisos | B8: 15725 | C8: 8045
A9: Tintas | B9: 10401 | C9: 5301
A10: Hidráulica | B10: 8241 | C10: 4076
A11: Elétrica | B11: 7705 | C11: 3844
A12: Madeiras | B12: 6234 | C12: 3016
A13: Ferramentas | B13: 5530 | C13: 2780
A14: Ferragens | B14: 3696 | C14: 1792

Sheet E25
A1: « Voltar ao índice
A2: 25) A maior e a menor loja lado a lado (mesma escala)
A3: Os dois gráficos usam o mesmo eixo de valores: a diferença de tamanho entre as lojas fica visível.
A4: Como criar no ThinQQ: Inserir gráfico > Colunas > Colunas agrupadas (duas vezes); Mais opções > Mesma escala. Valores: R$ mil.
E5: Aurora Centro (R$ mil) | L5: Rio Turquesa (R$ mil)
A6: Aurora Centro | B6: Vendas | C6: Custo
A7: 2024 | B7: 23324 | C7: 16040
A8: 2025 | B8: 26200 | C8: 18013
A11: Rio Turquesa | B11: Vendas | C11: Custo
A12: 2024 | B12: 8715 | C12: 6052
A13: 2025 | B13: 9435 | C13: 6546

Sheet E26
A1: « Voltar ao índice
A2: 26) Vendas mensais da loja Aurora Centro (sem legenda)
A3: Com uma série só, a legenda é dispensável: o título da planilha já diz o que é.
A4: Como criar no ThinQQ: Inserir gráfico > Linha e área > Linha; Legenda > Nenhuma. Valores: R$ mil.
A6: Mês | B6: Vendas
A7: 45658 | B7: 2072
A8: 45689 | B8: 1976
A9: 45717 | B9: 1903
A10: 45748 | B10: 1890
A11: 45778 | B11: 1950
A12: 45809 | B12: 2094
A13: 45839 | B13: 2248
A14: 45870 | B14: 2332
A15: 45901 | B15: 2372
A16: 45931 | B16: 2444
A17: 45962 | B17: 2467
A18: 45992 | B18: 2450

Sheet E27
A1: « Voltar ao índice
A2: 27) Da receita ao lucro, 2024 x 2025 (cascata comparativa)
A3: As duas pontes lado a lado, 2024 à esquerda e 2025 à direita, com os anos escritos dentro das barras da receita. A seta de cada etapa mostra quanto 2025 variou sobre 2024, (2025 - 2024) / 2024 (num custo, "+" quer dizer que o custo cresceu), e o lucro mostra o percentual da receita do próprio ano. Tudo acompanha os números, com ou sem o ThinQQ.
A4: Como criar no ThinQQ: Inserir gráfico > Cascata > Cascata comparativa (Setas de variação e Nome dentro das barras já vêm ligados). Valores: R$ milhões.
A6: Etapa | B6: 2024 | C6: 2025
A7: Receita bruta | B7: 117.2 | C7: 129.7
A8: Custo das mercadorias | B8: -79.9 | C8: -88.3
A9: Despesas operacionais | B9: -24.6 | C9: -27.2
A10: EBITDA | B10: e | C10: e
A11: Depreciação e juros | B11: -2.9 | C11: -3.2
A12: Impostos | B12: -3.3 | C12: -3.7
A13: Lucro líquido | B13: e | C13: e

Sheet E28
A1: « Voltar ao índice
A2: 28) As duas maiores lojas: da receita ao lucro em 2025 (variação em valor)
A3: A mesma ponte para as duas lojas que mais venderam em 2025; a seta de cada etapa mostra a diferença em R$ milhões entre a segunda loja e a primeira, e os nomes das lojas ficam na legenda.
A4: Como criar no ThinQQ: Inserir gráfico > Cascata > Cascata comparativa; Setas > Variação em valor; Legenda > Direita. Valores: R$ milhões.
A6: Etapa | B6: Aurora Centro | C6: Porto Sereno
A7: Receita bruta | B7: 26.2 | C7: 21.1
A8: Custo das mercadorias | B8: -18 | C8: -14.1
A9: Despesas operacionais | B9: -5.5 | C9: -4.4
A10: EBITDA | B10: e | C10: e
A11: Depreciação e juros | B11: -0.7 | C11: -0.5
A12: Impostos | B12: -0.7 | C12: -0.7
A13: Lucro líquido | B13: e | C13: e

Sheet _ThinQQ
A1: ThinQQ - planilha interna de cálculo. Não editar.
A3: 6lcho3 | B3: stacked | C3: ="'E01'!$A$6:$C$14" -> 'E01'!$A$6:$C$14 | D3: numfmt=int;palette=padrao;n=8;legend=right;gap=50;labels=1;totals=1;connectors=0
A4: Categoria | B4: Total | C4: TotalPos | D4: Pos | E4: VLine
A5: ='E01'!$A$7 -> Cimento e argamassa | B5: =_xlfn.AGGREGATE(9,6,'E01'!$B$7:$C$7) -> 43324 | C5: =IF(SUMIF('E01'!$B$7:$C$7,">0")>0,SUMIF('E01'!$B$7:$C$7,">0"),SUMIF('E01'!$B$7:$C$7,"<0")) -> 43324 | D5: =7.5 -> 7.5 | E5: =AVERAGE($B$5:$B$12) -> 16213.75
A6: ='E01'!$A$8 -> Pisos | B6: =_xlfn.AGGREGATE(9,6,'E01'!$B$8:$C$8) -> 23770 | C6: =IF(SUMIF('E01'!$B$8:$C$8,">0")>0,SUMIF('E01'!$B$8:$C$8,">0"),SUMIF('E01'!$B$8:$C$8,"<0")) -> 23770 | D6: =6.5 -> 6.5 | E6: =AVERAGE($B$5:$B$12) -> 16213.75
A7: ='E01'!$A$9 -> Tintas | B7: =_xlfn.AGGREGATE(9,6,'E01'!$B$9:$C$9) -> 15702 | C7: =IF(SUMIF('E01'!$B$9:$C$9,">0")>0,SUMIF('E01'!$B$9:$C$9,">0"),SUMIF('E01'!$B$9:$C$9,"<0")) -> 15702 | D7: =5.5 -> 5.5 | E7: =AVERAGE($B$5:$B$12) -> 16213.75
A8: ='E01'!$A$10 -> Hidráulica | B8: =_xlfn.AGGREGATE(9,6,'E01'!$B$10:$C$10) -> 12317 | C8: =IF(SUMIF('E01'!$B$10:$C$10,">0")>0,SUMIF('E01'!$B$10:$C$10,">0"),SUMIF('E01'!$B$10:$C$10,"<0")) -> 12317 | D8: =4.5 -> 4.5 | E8: =AVERAGE($B$5:$B$12) -> 16213.75
A9: ='E01'!$A$11 -> Elétrica | B9: =_xlfn.AGGREGATE(9,6,'E01'!$B$11:$C$11) -> 11549 | C9: =IF(SUMIF('E01'!$B$11:$C$11,">0")>0,SUMIF('E01'!$B$11:$C$11,">0"),SUMIF('E01'!$B$11:$C$11,"<0")) -> 11549 | D9: =3.5 -> 3.5 | E9: =AVERAGE($B$5:$B$12) -> 16213.75
A10: ='E01'!$A$12 -> Madeiras | B10: =_xlfn.AGGREGATE(9,6,'E01'!$B$12:$C$12) -> 9250 | C10: =IF(SUMIF('E01'!$B$12:$C$12,">0")>0,SUMIF('E01'!$B$12:$C$12,">0"),SUMIF('E01'!$B$12:$C$12,"<0")) -> 9250 | D10: =2.5 -> 2.5 | E10: =AVERAGE($B$5:$B$12) -> 16213.75
A11: ='E01'!$A$13 -> Ferramentas | B11: =_xlfn.AGGREGATE(9,6,'E01'!$B$13:$C$13) -> 8310 | C11: =IF(SUMIF('E01'!$B$13:$C$13,">0")>0,SUMIF('E01'!$B$13:$C$13,">0"),SUMIF('E01'!$B$13:$C$13,"<0")) -> 8310 | D11: =1.5 -> 1.5 | E11: =AVERAGE($B$5:$B$12) -> 16213.75
A12: ='E01'!$A$14 -> Ferragens | B12: =_xlfn.AGGREGATE(9,6,'E01'!$B$14:$C$14) -> 5488 | C12: =IF(SUMIF('E01'!$B$14:$C$14,">0")>0,SUMIF('E01'!$B$14:$C$14,">0"),SUMIF('E01'!$B$14:$C$14,"<0")) -> 5488 | D12: =0.5 -> 0.5 | E12: =AVERAGE($B$5:$B$12) -> 16213.75
A14: 24phpw | B14: clustered | C14: ="'E02'!$A$6:$C$14" -> 'E02'!$A$6:$C$14 | D14: numfmt=dec1;palette=padrao;n=8;legend=right;gap=120;labels=1;totals=0;connectors=0
A15: Categoria | B15: Total | C15: TotalPos | D15: Pos | E15: VLine
A16: ='E02'!$A$7 -> Aurora Centro | B16: =_xlfn.AGGREGATE(9,6,'E02'!$B$7:$C$7) -> 49.5 | C16: =B16 -> 49.5 | D16: =7.5 -> 7.5 | E16: =IFERROR(_xlfn.AGGREGATE(1,6,'E02'!$B$7:$C$14),0) -> 15.43125
A17: ='E02'!$A$8 -> Porto Sereno | B17: =_xlfn.AGGREGATE(9,6,'E02'!$B$8:$C$8) -> 39.6 | C17: =B17 -> 39.6 | D17: =6.5 -> 6.5 | E17: =IFERROR(_xlfn.AGGREGATE(1,6,'E02'!$B$7:$C$14),0) -> 15.43125
A18: ='E02'!$A$9 -> Campo Dourado | B18: =_xlfn.AGGREGATE(9,6,'E02'!$B$9:$C$9) -> 33.9 | C18: =B18 -> 33.9 | D18: =5.5 -> 5.5 | E18: =IFERROR(_xlfn.AGGREGATE(1,6,'E02'!$B$7:$C$14),0) -> 15.43125
A19: ='E02'!$A$10 -> Aurora Norte | B19: =_xlfn.AGGREGATE(9,6,'E02'!$B$10:$C$10) -> 30.9 | C19: =B19 -> 30.9 | D19: =4.5 -> 4.5 | E19: =IFERROR(_xlfn.AGGREGATE(1,6,'E02'!$B$7:$C$14),0) -> 15.43125
A20: ='E02'!$A$11 -> Lago Prateado | B20: =_xlfn.AGGREGATE(9,6,'E02'!$B$11:$C$11) -> 27.9 | C20: =B20 -> 27.9 | D20: =3.5 -> 3.5 | E20: =IFERROR(_xlfn.AGGREGATE(1,6,'E02'!$B$7:$C$14),0) -> 15.43125
A21: ='E02'!$A$12 -> Serra Clara | B21: =_xlfn.AGGREGATE(9,6,'E02'!$B$12:$C$12) -> 25.9 | C21: =B21 -> 25.9 | D21: =2.5 -> 2.5 | E21: =IFERROR(_xlfn.AGGREGATE(1,6,'E02'!$B$7:$C$14),0) -> 15.43125
A22: ='E02'!$A$13 -> Monte Alvorada | B22: =_xlfn.AGGREGATE(9,6,'E02'!$B$13:$C$13) -> 21.1 | C22: =B22 -> 21.1 | D22: =1.5 -> 1.5 | E22: =IFERROR(_xlfn.AGGREGATE(1,6,'E02'!$B$7:$C$14),0) -> 15.43125
A23: ='E02'!$A$14 -> Rio Turquesa | B23: =_xlfn.AGGREGATE(9,6,'E02'!$B$14:$C$14) -> 18.1 | C23: =B23 -> 18.1 | D23: =0.5 -> 0.5 | E23: =IFERROR(_xlfn.AGGREGATE(1,6,'E02'!$B$7:$C$14),0) -> 15.43125
A25: dqi1le | B25: stacked100 | C25: ="'E03'!$A$6:$C$11" -> 'E03'!$A$6:$C$11 | D25: numfmt=int;palette=padrao;n=5;legend=right;gap=50;labels=1;totals=1;connectors=0;ind100=1
A26: Categoria | B26: Total | C26: TotalPos | D26: Part1 | E26: Part2 | F26: Pos | G26: VLine
A27: ='E03'!$A$7 -> Sudeste | B27: =_xlfn.AGGREGATE(9,6,'E03'!$B$7:$C$7) -> 42264 | C27: =1 -> 1 | D27: =IF(AND(ISNUMBER('E03'!$B$7),B27<>0),'E03'!$B$7/B27,0) -> 0.60753833 | E27: =IF(AND(ISNUMBER('E03'!$C$7),B27<>0),'E03'!$C$7/B27,0) -> 0.39246167 | F27: =4.5 -> 4.5 | G27: =NA() -> #N/A
A28: ='E03'!$A$8 -> Sul | B28: =_xlfn.AGGREGATE(9,6,'E03'!$B$8:$C$8) -> 34905 | C28: =1 -> 1 | D28: =IF(AND(ISNUMBER('E03'!$B$8),B28<>0),'E03'!$B$8/B28,0) -> 0.67096405 | E28: =IF(AND(ISNUMBER('E03'!$C$8),B28<>0),'E03'!$C$8/B28,0) -> 0.32903595 | F28: =3.5 -> 3.5 | G28: =NA() -> #N/A
A29: ='E03'!$A$9 -> Nordeste | B29: =_xlfn.AGGREGATE(9,6,'E03'!$B$9:$C$9) -> 25450 | C29: =1 -> 1 | D29: =IF(AND(ISNUMBER('E03'!$B$9),B29<>0),'E03'!$B$9/B29,0) -> 0.75776031 | E29: =IF(AND(ISNUMBER('E03'!$C$9),B29<>0),'E03'!$C$9/B29,0) -> 0.24223969 | F29: =2.5 -> 2.5 | G29: =NA() -> #N/A
A30: ='E03'!$A$10 -> Centro-Oeste | B30: =_xlfn.AGGREGATE(9,6,'E03'!$B$10:$C$10) -> 17656 | C30: =1 -> 1 | D30: =IF(AND(ISNUMBER('E03'!$B$10),B30<>0),'E03'!$B$10/B30,0) -> 0.68934073 | E30: =IF(AND(ISNUMBER('E03'!$C$10),B30<>0),'E03'!$C$10/B30,0) -> 0.31065927 | F30: =1.5 -> 1.5 | G30: =NA() -> #N/A
A31: ='E03'!$A$11 -> Norte | B31: =_xlfn.AGGREGATE(9,6,'E03'!$B$11:$C$11) -> 9435 | C31: =1 -> 1 | D31: =IF(AND(ISNUMBER('E03'!$B$11),B31<>0),'E03'!$B$11/B31,0) -> 0.6609433 | E31: =IF(AND(ISNUMBER('E03'!$C$11),B31<>0),'E03'!$C$11/B31,0) -> 0.3390567 | F31: =0.5 -> 0.5 | G31: =NA() -> #N/A
A33: w0j8na | B33: line | C33: ="'E04'!$A$6:$C$18" -> 'E04'!$A$6:$C$18 | D33: numfmt=int;palette=padrao;n=12;legend=lineend;labels=1;totals=0;connectors=0
A34: Categoria | B34: Total | C34: TotalPos | D34: Pos | E34: VLine
A35: ='E04'!$A$7 -> 45658 | B35: =_xlfn.AGGREGATE(9,6,'E04'!$B$7:$C$7) -> 3492 | C35: =B35 -> 3492 | D35: =11.5 -> 11.5 | E35: =IFERROR(_xlfn.AGGREGATE(1,6,'E04'!$B$7:$C$18),0) -> 1842.125
A36: ='E04'!$A$8 -> 45689 | B36: =_xlfn.AGGREGATE(9,6,'E04'!$B$8:$C$8) -> 3341 | C36: =B36 -> 3341 | D36: =10.5 -> 10.5 | E36: =IFERROR(_xlfn.AGGREGATE(1,6,'E04'!$B$7:$C$18),0) -> 1842.125
A37: ='E04'!$A$9 -> 45717 | B37: =_xlfn.AGGREGATE(9,6,'E04'!$B$9:$C$9) -> 3211 | C37: =B37 -> 3211 | D37: =9.5 -> 9.5 | E37: =IFERROR(_xlfn.AGGREGATE(1,6,'E04'!$B$7:$C$18),0) -> 1842.125
A38: ='E04'!$A$10 -> 45748 | B38: =_xlfn.AGGREGATE(9,6,'E04'!$B$10:$C$10) -> 3185 | C38: =B38 -> 3185 | D38: =8.5 -> 8.5 | E38: =IFERROR(_xlfn.AGGREGATE(1,6,'E04'!$B$7:$C$18),0) -> 1842.125
A39: ='E04'!$A$11 -> 45778 | B39: =_xlfn.AGGREGATE(9,6,'E04'!$B$11:$C$11) -> 3297 | C39: =B39 -> 3297 | D39: =7.5 -> 7.5 | E39: =IFERROR(_xlfn.AGGREGATE(1,6,'E04'!$B$7:$C$18),0) -> 1842.125
A40: ='E04'!$A$12 -> 45809 | B40: =_xlfn.AGGREGATE(9,6,'E04'!$B$12:$C$12) -> 3536 | C40: =B40 -> 3536 | D40: =6.5 -> 6.5 | E40: =IFERROR(_xlfn.AGGREGATE(1,6,'E04'!$B$7:$C$18),0) -> 1842.125
A41: ='E04'!$A$13 -> 45839 | B41: =_xlfn.AGGREGATE(9,6,'E04'!$B$13:$C$13) -> 3794 | C41: =B41 -> 3794 | D41: =5.5 -> 5.5 | E41: =IFERROR(_xlfn.AGGREGATE(1,6,'E04'!$B$7:$C$18),0) -> 1842.125
A42: ='E04'!$A$14 -> 45870 | B42: =_xlfn.AGGREGATE(9,6,'E04'!$B$14:$C$14) -> 3947 | C42: =B42 -> 3947 | D42: =4.5 -> 4.5 | E42: =IFERROR(_xlfn.AGGREGATE(1,6,'E04'!$B$7:$C$18),0) -> 1842.125
A43: ='E04'!$A$15 -> 45901 | B43: =_xlfn.AGGREGATE(9,6,'E04'!$B$15:$C$15) -> 3992 | C43: =B43 -> 3992 | D43: =3.5 -> 3.5 | E43: =IFERROR(_xlfn.AGGREGATE(1,6,'E04'!$B$7:$C$18),0) -> 1842.125
A44: ='E04'!$A$16 -> 45931 | B44: =_xlfn.AGGREGATE(9,6,'E04'!$B$16:$C$16) -> 4118 | C44: =B44 -> 4118 | D44: =2.5 -> 2.5 | E44: =IFERROR(_xlfn.AGGREGATE(1,6,'E04'!$B$7:$C$18),0) -> 1842.125
A45: ='E04'!$A$17 -> 45962 | B45: =_xlfn.AGGREGATE(9,6,'E04'!$B$17:$C$17) -> 4159 | C45: =B45 -> 4159 | D45: =1.5 -> 1.5 | E45: =IFERROR(_xlfn.AGGREGATE(1,6,'E04'!$B$7:$C$18),0) -> 1842.125
A46: ='E04'!$A$18 -> 45992 | B46: =_xlfn.AGGREGATE(9,6,'E04'!$B$18:$C$18) -> 4139 | C46: =B46 -> 4139 | D46: =0.5 -> 0.5 | E46: =IFERROR(_xlfn.AGGREGATE(1,6,'E04'!$B$7:$C$18),0) -> 1842.125
A48: d37c54 | B48: waterfall | C48: ="'E05'!$A$6:$B$13" -> 'E05'!$A$6:$B$13 | D48: numfmt=int;palette=padrao;gap=50;totals=0;n=7;labels=1;connectors=1
A49: Cat | B49: Src | C49: IsTotal | D49: Delta | E49: Start | F49: End | G49: Lo | H49: Hi | I49: Base | J49: PiecePos | K49: PieceNeg | L49: UpPos | M49: UpNeg | N49: DownPos | O49: DownNeg | P49: Total | Q49: LabelVal | R49: LabelPos | S49: Pos | T49: BD
A50: ='E05'!$A$7 -> Receita bruta | B50: ='E05'!$B$7 -> 129710 | C50: =IF(ISERROR(B50),FALSE,IF(ISNUMBER(B50),FALSE,OR(LOWER(TRIM(B50&""))={"e","t","=","total","subtotal"}))) -> FALSE | D50: =IF(C50,0,IF(ISNUMBER(B50),B50,0)) -> 129710 | E50: =0 -> 0 | F50: =IF($T50,_xlfn.AGGREGATE(9,6,'E05'!$B$13)-SUM($D51:$D55),$E50+$D50) -> 129710 | G50: =IF(C50,MIN(0,F50),MIN(E50,F50)) -> 0 | H50: =IF(C50,MAX(0,F50),MAX(E50,F50)) -> 129710 | I50: =MAX(0,G50)+MIN(0,H50) -> 0 | J50: =MAX(0,H50)-MAX(0,G50) -> 129710 | K50: =MIN(0,G50)-MIN(0,H50) -> 0 | L50: =IF(AND(NOT(C50),D50>=0),J50,0) -> 129710 | M50: =IF(AND(NOT(C50),D50>=0),K50,0) -> 0 | N50: =IF(AND(NOT(C50),D50<0),J50,0) -> 0 | O50: =IF(AND(NOT(C50),D50<0),K50,0) -> 0 | P50: =IF(C50,F50,0) -> 0 | Q50: =IF(C50,F50,D50) -> 129710 | R50: =IF(Q50>=0,H50,G50) -> 129710 | S50: =6.5 -> 6.5 | T50: =AND(IF(ISERROR('E05'!$B$7),FALSE,IF(ISNUMBER('E05'!$B$7),FALSE,OR(LOWER(TRIM('E05'!$B$7&""))={"e","t","=","total","subtotal"}))),COUNT('E05'!$B$13)>0,NOT(IF(ISERROR('E05'!$B$13),FALSE,IF(ISNUMBER('E05'!$B$13),FALSE,OR(LOWER(TRIM('E05'!$B$13&""))={"e","t","=","total","subtotal"}))))) -> FALSE
A51: ='E05'!$A$8 -> Custo das mercadorias | B51: ='E05'!$B$8 -> -88293 | C51: =IF(ISERROR(B51),FALSE,IF(ISNUMBER(B51),FALSE,OR(LOWER(TRIM(B51&""))={"e","t","=","total","subtotal"}))) -> FALSE | D51: =IF(C51,0,IF(ISNUMBER(B51),B51,0)) -> -88293 | E51: =F50 -> 129710 | F51: =$E51+$D51 -> 41417 | G51: =IF(C51,MIN(0,F51),MIN(E51,F51)) -> 41417 | H51: =IF(C51,MAX(0,F51),MAX(E51,F51)) -> 129710 | I51: =MAX(0,G51)+MIN(0,H51) -> 41417 | J51: =MAX(0,H51)-MAX(0,G51) -> 88293 | K51: =MIN(0,G51)-MIN(0,H51) -> 0 | L51: =IF(AND(NOT(C51),D51>=0),J51,0) -> 0 | M51: =IF(AND(NOT(C51),D51>=0),K51,0) -> 0 | N51: =IF(AND(NOT(C51),D51<0),J51,0) -> 88293 | O51: =IF(AND(NOT(C51),D51<0),K51,0) -> 0 | P51: =IF(C51,F51,0) -> 0 | Q51: =IF(C51,F51,D51) -> -88293 | R51: =IF(Q51>=0,H51,G51) -> 41417 | S51: =5.5 -> 5.5 | T51: =AND(IF(ISERROR('E05'!$B$7),FALSE,IF(ISNUMBER('E05'!$B$7),FALSE,OR(LOWER(TRIM('E05'!$B$7&""))={"e","t","=","total","subtotal"}))),COUNT('E05'!$B$13)>0,NOT(IF(ISERROR('E05'!$B$13),FALSE,IF(ISNUMBER('E05'!$B$13),FALSE,OR(LOWER(TRIM('E05'!$B$13&""))={"e","t","=","total","subtotal"}))))) -> FALSE
A52: ='E05'!$A$9 -> Despesas operacionais | B52: ='E05'!$B$9 -> -27239 | C52: =IF(ISERROR(B52),FALSE,IF(ISNUMBER(B52),FALSE,OR(LOWER(TRIM(B52&""))={"e","t","=","total","subtotal"}))) -> FALSE | D52: =IF(C52,0,IF(ISNUMBER(B52),B52,0)) -> -27239 | E52: =F51 -> 41417 | F52: =$E52+$D52 -> 14178 | G52: =IF(C52,MIN(0,F52),MIN(E52,F52)) -> 14178 | H52: =IF(C52,MAX(0,F52),MAX(E52,F52)) -> 41417 | I52: =MAX(0,G52)+MIN(0,H52) -> 14178 | J52: =MAX(0,H52)-MAX(0,G52) -> 27239 | K52: =MIN(0,G52)-MIN(0,H52) -> 0 | L52: =IF(AND(NOT(C52),D52>=0),J52,0) -> 0 | M52: =IF(AND(NOT(C52),D52>=0),K52,0) -> 0 | N52: =IF(AND(NOT(C52),D52<0),J52,0) -> 27239 | O52: =IF(AND(NOT(C52),D52<0),K52,0) -> 0 | P52: =IF(C52,F52,0) -> 0 | Q52: =IF(C52,F52,D52) -> -27239 | R52: =IF(Q52>=0,H52,G52) -> 14178 | S52: =4.5 -> 4.5 | T52: =AND(IF(ISERROR('E05'!$B$7),FALSE,IF(ISNUMBER('E05'!$B$7),FALSE,OR(LOWER(TRIM('E05'!$B$7&""))={"e","t","=","total","subtotal"}))),COUNT('E05'!$B$13)>0,NOT(IF(ISERROR('E05'!$B$13),FALSE,IF(ISNUMBER('E05'!$B$13),FALSE,OR(LOWER(TRIM('E05'!$B$13&""))={"e","t","=","total","subtotal"}))))) -> FALSE
A53: ='E05'!$A$10 -> EBITDA | B53: ='E05'!$B$10 -> e | C53: =IF(ISERROR(B53),FALSE,IF(ISNUMBER(B53),FALSE,OR(LOWER(TRIM(B53&""))={"e","t","=","total","subtotal"}))) -> TRUE | D53: =IF(C53,0,IF(ISNUMBER(B53),B53,0)) -> 0 | E53: =F52 -> 14178 | F53: =$E53+$D53 -> 14178 | G53: =IF(C53,MIN(0,F53),MIN(E53,F53)) -> 0 | H53: =IF(C53,MAX(0,F53),MAX(E53,F53)) -> 14178 | I53: =MAX(0,G53)+MIN(0,H53) -> 0 | J53: =MAX(0,H53)-MAX(0,G53) -> 14178 | K53: =MIN(0,G53)-MIN(0,H53) -> 0 | L53: =IF(AND(NOT(C53),D53>=0),J53,0) -> 0 | M53: =IF(AND(NOT(C53),D53>=0),K53,0) -> 0 | N53: =IF(AND(NOT(C53),D53<0),J53,0) -> 0 | O53: =IF(AND(NOT(C53),D53<0),K53,0) -> 0 | P53: =IF(C53,F53,0) -> 14178 | Q53: =IF(C53,F53,D53) -> 14178 | R53: =IF(Q53>=0,H53,G53) -> 14178 | S53: =3.5 -> 3.5 | T53: =AND(IF(ISERROR('E05'!$B$7),FALSE,IF(ISNUMBER('E05'!$B$7),FALSE,OR(LOWER(TRIM('E05'!$B$7&""))={"e","t","=","total","subtotal"}))),COUNT('E05'!$B$13)>0,NOT(IF(ISERROR('E05'!$B$13),FALSE,IF(ISNUMBER('E05'!$B$13),FALSE,OR(LOWER(TRIM('E05'!$B$13&""))={"e","t","=","total","subtotal"}))))) -> FALSE
A54: ='E05'!$A$11 -> Depreciação e juros | B54: ='E05'!$B$11 -> -3243 | C54: =IF(ISERROR(B54),FALSE,IF(ISNUMBER(B54),FALSE,OR(LOWER(TRIM(B54&""))={"e","t","=","total","subtotal"}))) -> FALSE | D54: =IF(C54,0,IF(ISNUMBER(B54),B54,0)) -> -3243 | E54: =F53 -> 14178 | F54: =$E54+$D54 -> 10935 | G54: =IF(C54,MIN(0,F54),MIN(E54,F54)) -> 10935 | H54: =IF(C54,MAX(0,F54),MAX(E54,F54)) -> 14178 | I54: =MAX(0,G54)+MIN(0,H54) -> 10935 | J54: =MAX(0,H54)-MAX(0,G54) -> 3243 | K54: =MIN(0,G54)-MIN(0,H54) -> 0 | L54: =IF(AND(NOT(C54),D54>=0),J54,0) -> 0 | M54: =IF(AND(NOT(C54),D54>=0),K54,0) -> 0 | N54: =IF(AND(NOT(C54),D54<0),J54,0) -> 3243 | O54: =IF(AND(NOT(C54),D54<0),K54,0) -> 0 | P54: =IF(C54,F54,0) -> 0 | Q54: =IF(C54,F54,D54) -> -3243 | R54: =IF(Q54>=0,H54,G54) -> 10935 | S54: =2.5 -> 2.5 | T54: =AND(IF(ISERROR('E05'!$B$7),FALSE,IF(ISNUMBER('E05'!$B$7),FALSE,OR(LOWER(TRIM('E05'!$B$7&""))={"e","t","=","total","subtotal"}))),COUNT('E05'!$B$13)>0,NOT(IF(ISERROR('E05'!$B$13),FALSE,IF(ISNUMBER('E05'!$B$13),FALSE,OR(LOWER(TRIM('E05'!$B$13&""))={"e","t","=","total","subtotal"}))))) -> FALSE
A55: ='E05'!$A$12 -> Impostos | B55: ='E05'!$B$12 -> -3718 | C55: =IF(ISERROR(B55),FALSE,IF(ISNUMBER(B55),FALSE,OR(LOWER(TRIM(B55&""))={"e","t","=","total","subtotal"}))) -> FALSE | D55: =IF(C55,0,IF(ISNUMBER(B55),B55,0)) -> -3718 | E55: =F54 -> 10935 | F55: =$E55+$D55 -> 7217 | G55: =IF(C55,MIN(0,F55),MIN(E55,F55)) -> 7217 | H55: =IF(C55,MAX(0,F55),MAX(E55,F55)) -> 10935 | I55: =MAX(0,G55)+MIN(0,H55) -> 7217 | J55: =MAX(0,H55)-MAX(0,G55) -> 3718 | K55: =MIN(0,G55)-MIN(0,H55) -> 0 | L55: =IF(AND(NOT(C55),D55>=0),J55,0) -> 0 | M55: =IF(AND(NOT(C55),D55>=0),K55,0) -> 0 | N55: =IF(AND(NOT(C55),D55<0),J55,0) -> 3718 | O55: =IF(AND(NOT(C55),D55<0),K55,0) -> 0 | P55: =IF(C55,F55,0) -> 0 | Q55: =IF(C55,F55,D55) -> -3718 | R55: =IF(Q55>=0,H55,G55) -> 7217 | S55: =1.5 -> 1.5 | T55: =AND(IF(ISERROR('E05'!$B$7),FALSE,IF(ISNUMBER('E05'!$B$7),FALSE,OR(LOWER(TRIM('E05'!$B$7&""))={"e","t","=","total","subtotal"}))),COUNT('E05'!$B$13)>0,NOT(IF(ISERROR('E05'!$B$13),FALSE,IF(ISNUMBER('E05'!$B$13),FALSE,OR(LOWER(TRIM('E05'!$B$13&""))={"e","t","=","total","subtotal"}))))) -> FALSE
A56: ='E05'!$A$13 -> Lucro líquido | B56: ='E05'!$B$13 -> e | C56: =OR(IF(ISERROR('E05'!$B$13),FALSE,IF(ISNUMBER('E05'!$B$13),FALSE,OR(LOWER(TRIM('E05'!$B$13&""))={"e","t","=","total","subtotal"}))),$T56) -> TRUE | D56: =IF(C56,0,IF(ISNUMBER(B56),B56,0)) -> 0 | E56: =F55 -> 7217 | F56: =IF($T56,_xlfn.AGGREGATE(9,6,'E05'!$B$13),$E56+$D56) -> 7217 | G56: =IF(C56,MIN(0,F56),MIN(E56,F56)) -> 0 | H56: =IF(C56,MAX(0,F56),MAX(E56,F56)) -> 7217 | I56: =MAX(0,G56)+MIN(0,H56) -> 0 | J56: =MAX(0,H56)-MAX(0,G56) -> 7217 | K56: =MIN(0,G56)-MIN(0,H56) -> 0 | L56: =IF(AND(NOT(C56),D56>=0),J56,0) -> 0 | M56: =IF(AND(NOT(C56),D56>=0),K56,0) -> 0 | N56: =IF(AND(NOT(C56),D56<0),J56,0) -> 0 | O56: =IF(AND(NOT(C56),D56<0),K56,0) -> 0 | P56: =IF(C56,F56,0) -> 7217 | Q56: =IF(C56,F56,D56) -> 7217 | R56: =IF(Q56>=0,H56,G56) -> 7217 | S56: =0.5 -> 0.5 | T56: =AND(IF(ISERROR('E05'!$B$7),FALSE,IF(ISNUMBER('E05'!$B$7),FALSE,OR(LOWER(TRIM('E05'!$B$7&""))={"e","t","=","total","subtotal"}))),COUNT('E05'!$B$13)>0,NOT(IF(ISERROR('E05'!$B$13),FALSE,IF(ISNUMBER('E05'!$B$13),FALSE,OR(LOWER(TRIM('E05'!$B$13&""))={"e","t","=","total","subtotal"}))))) -> FALSE
A58: 9013ju | B58: barstacked | C58: ="'E06'!$A$6:$C$11" -> 'E06'!$A$6:$C$11 | D58: numfmt=int;palette=padrao;n=5;legend=right;gap=50;labels=1;totals=1;connectors=0
A59: Categoria | B59: Total | C59: TotalPos | D59: Pos | E59: VLine
A60: ='E06'!$A$7 -> Sudeste | B60: =_xlfn.AGGREGATE(9,6,'E06'!$B$7:$C$7) -> 42264 | C60: =IF(SUMIF('E06'!$B$7:$C$7,">0")>0,SUMIF('E06'!$B$7:$C$7,">0"),SUMIF('E06'!$B$7:$C$7,"<0")) -> 42264 | D60: =4.5 -> 4.5 | E60: =AVERAGE($B$60:$B$64) -> 25942
A61: ='E06'!$A$8 -> Sul | B61: =_xlfn.AGGREGATE(9,6,'E06'!$B$8:$C$8) -> 34905 | C61: =IF(SUMIF('E06'!$B$8:$C$8,">0")>0,SUMIF('E06'!$B$8:$C$8,">0"),SUMIF('E06'!$B$8:$C$8,"<0")) -> 34905 | D61: =3.5 -> 3.5 | E61: =AVERAGE($B$60:$B$64) -> 25942
A62: ='E06'!$A$9 -> Nordeste | B62: =_xlfn.AGGREGATE(9,6,'E06'!$B$9:$C$9) -> 25450 | C62: =IF(SUMIF('E06'!$B$9:$C$9,">0")>0,SUMIF('E06'!$B$9:$C$9,">0"),SUMIF('E06'!$B$9:$C$9,"<0")) -> 25450 | D62: =2.5 -> 2.5 | E62: =AVERAGE($B$60:$B$64) -> 25942
A63: ='E06'!$A$10 -> Centro-Oeste | B63: =_xlfn.AGGREGATE(9,6,'E06'!$B$10:$C$10) -> 17656 | C63: =IF(SUMIF('E06'!$B$10:$C$10,">0")>0,SUMIF('E06'!$B$10:$C$10,">0"),SUMIF('E06'!$B$10:$C$10,"<0")) -> 17656 | D63: =1.5 -> 1.5 | E63: =AVERAGE($B$60:$B$64) -> 25942
A64: ='E06'!$A$11 -> Norte | B64: =_xlfn.AGGREGATE(9,6,'E06'!$B$11:$C$11) -> 9435 | C64: =IF(SUMIF('E06'!$B$11:$C$11,">0")>0,SUMIF('E06'!$B$11:$C$11,">0"),SUMIF('E06'!$B$11:$C$11,"<0")) -> 9435 | D64: =0.5 -> 0.5 | E64: =AVERAGE($B$60:$B$64) -> 25942
A66: t3w2hb | B66: barclustered | C66: ="'E07'!$A$6:$C$14" -> 'E07'!$A$6:$C$14 | D66: numfmt=mil;palette=padrao;n=8;legend=right;gap=80;labels=1;totals=0;connectors=0
A67: Categoria | B67: Total | C67: TotalPos | D67: Pos | E67: VLine
A68: ='E07'!$A$7 -> Aurora Centro | B68: =_xlfn.AGGREGATE(9,6,'E07'!$B$7:$C$7) -> 49524057 | C68: =B68 -> 49524057 | D68: =7.5 -> 7.5 | E68: =IFERROR(_xlfn.AGGREGATE(1,6,'E07'!$B$7:$C$14),0) -> 15433387
A69: ='E07'!$A$8 -> Porto Sereno | B69: =_xlfn.AGGREGATE(9,6,'E07'!$B$8:$C$8) -> 39565143 | C69: =B69 -> 39565143 | D69: =6.5 -> 6.5 | E69: =IFERROR(_xlfn.AGGREGATE(1,6,'E07'!$B$7:$C$14),0) -> 15433387
A70: ='E07'!$A$9 -> Campo Dourado | B70: =_xlfn.AGGREGATE(9,6,'E07'!$B$9:$C$9) -> 33893051 | C70: =B70 -> 33893051 | D70: =5.5 -> 5.5 | E70: =IFERROR(_xlfn.AGGREGATE(1,6,'E07'!$B$7:$C$14),0) -> 15433387
A71: ='E07'!$A$10 -> Aurora Norte | B71: =_xlfn.AGGREGATE(9,6,'E07'!$B$10:$C$10) -> 30837367 | C71: =B71 -> 30837367 | D71: =4.5 -> 4.5 | E71: =IFERROR(_xlfn.AGGREGATE(1,6,'E07'!$B$7:$C$14),0) -> 15433387
A72: ='E07'!$A$11 -> Lago Prateado | B72: =_xlfn.AGGREGATE(9,6,'E07'!$B$11:$C$11) -> 27934127 | C72: =B72 -> 27934127 | D72: =3.5 -> 3.5 | E72: =IFERROR(_xlfn.AGGREGATE(1,6,'E07'!$B$7:$C$14),0) -> 15433387
A73: ='E07'!$A$12 -> Serra Clara | B73: =_xlfn.AGGREGATE(9,6,'E07'!$B$12:$C$12) -> 25906922 | C73: =B73 -> 25906922 | D73: =2.5 -> 2.5 | E73: =IFERROR(_xlfn.AGGREGATE(1,6,'E07'!$B$7:$C$14),0) -> 15433387
A74: ='E07'!$A$13 -> Monte Alvorada | B74: =_xlfn.AGGREGATE(9,6,'E07'!$B$13:$C$13) -> 21123064 | C74: =B74 -> 21123064 | D74: =1.5 -> 1.5 | E74: =IFERROR(_xlfn.AGGREGATE(1,6,'E07'!$B$7:$C$14),0) -> 15433387
A75: ='E07'!$A$14 -> Rio Turquesa | B75: =_xlfn.AGGREGATE(9,6,'E07'!$B$14:$C$14) -> 18150455 | C75: =B75 -> 18150455 | D75: =0.5 -> 0.5 | E75: =IFERROR(_xlfn.AGGREGATE(1,6,'E07'!$B$7:$C$14),0) -> 15433387
A77: pfbcck | B77: barstacked100 | C77: ="'E08'!$A$6:$C$14" -> 'E08'!$A$6:$C$14 | D77: numfmt=int;palette=padrao;n=8;legend=right;gap=50;labels=1;totals=1;connectors=0;ind100=1
A78: Categoria | B78: Total | C78: TotalPos | D78: Part1 | E78: Part2 | F78: Pos | G78: VLine
A79: ='E08'!$A$7 -> Aurora Centro | B79: =_xlfn.AGGREGATE(9,6,'E08'!$B$7:$C$7) -> 26200 | C79: =1 -> 1 | D79: =IF(AND(ISNUMBER('E08'!$B$7),B79<>0),'E08'!$B$7/B79,0) -> 0.56980916 | E79: =IF(AND(ISNUMBER('E08'!$C$7),B79<>0),'E08'!$C$7/B79,0) -> 0.43019084 | F79: =7.5 -> 7.5 | G79: =NA() -> #N/A
A80: ='E08'!$A$8 -> Porto Sereno | B80: =_xlfn.AGGREGATE(9,6,'E08'!$B$8:$C$8) -> 21085 | C80: =1 -> 1 | D80: =IF(AND(ISNUMBER('E08'!$B$8),B80<>0),'E08'!$B$8/B80,0) -> 0.76158406 | E80: =IF(AND(ISNUMBER('E08'!$C$8),B80<>0),'E08'!$C$8/B80,0) -> 0.23841594 | F80: =6.5 -> 6.5 | G80: =NA() -> #N/A
A81: ='E08'!$A$9 -> Campo Dourado | B81: =_xlfn.AGGREGATE(9,6,'E08'!$B$9:$C$9) -> 17656 | C81: =1 -> 1 | D81: =IF(AND(ISNUMBER('E08'!$B$9),B81<>0),'E08'!$B$9/B81,0) -> 0.68934073 | E81: =IF(AND(ISNUMBER('E08'!$C$9),B81<>0),'E08'!$C$9/B81,0) -> 0.31065927 | F81: =5.5 -> 5.5 | G81: =NA() -> #N/A
A82: ='E08'!$A$10 -> Aurora Norte | B82: =_xlfn.AGGREGATE(9,6,'E08'!$B$10:$C$10) -> 16064 | C82: =1 -> 1 | D82: =IF(AND(ISNUMBER('E08'!$B$10),B82<>0),'E08'!$B$10/B82,0) -> 0.66901145 | E82: =IF(AND(ISNUMBER('E08'!$C$10),B82<>0),'E08'!$C$10/B82,0) -> 0.33098855 | F82: =4.5 -> 4.5 | G82: =NA() -> #N/A
A83: ='E08'!$A$11 -> Lago Prateado | B83: =_xlfn.AGGREGATE(9,6,'E08'!$B$11:$C$11) -> 14532 | C83: =1 -> 1 | D83: =IF(AND(ISNUMBER('E08'!$B$11),B83<>0),'E08'!$B$11/B83,0) -> 0.78867327 | E83: =IF(AND(ISNUMBER('E08'!$C$11),B83<>0),'E08'!$C$11/B83,0) -> 0.21132673 | F83: =3.5 -> 3.5 | G83: =NA() -> #N/A
A84: ='E08'!$A$12 -> Serra Clara | B84: =_xlfn.AGGREGATE(9,6,'E08'!$B$12:$C$12) -> 13820 | C84: =1 -> 1 | D84: =IF(AND(ISNUMBER('E08'!$B$12),B84<>0),'E08'!$B$12/B84,0) -> 0.53270622 | E84: =IF(AND(ISNUMBER('E08'!$C$12),B84<>0),'E08'!$C$12/B84,0) -> 0.46729378 | F84: =2.5 -> 2.5 | G84: =NA() -> #N/A
A85: ='E08'!$A$13 -> Monte Alvorada | B85: =_xlfn.AGGREGATE(9,6,'E08'!$B$13:$C$13) -> 10918 | C85: =1 -> 1 | D85: =IF(AND(ISNUMBER('E08'!$B$13),B85<>0),'E08'!$B$13/B85,0) -> 0.71661476 | E85: =IF(AND(ISNUMBER('E08'!$C$13),B85<>0),'E08'!$C$13/B85,0) -> 0.28338524 | F85: =1.5 -> 1.5 | G85: =NA() -> #N/A
A86: ='E08'!$A$14 -> Rio Turquesa | B86: =_xlfn.AGGREGATE(9,6,'E08'!$B$14:$C$14) -> 9435 | C86: =1 -> 1 | D86: =IF(AND(ISNUMBER('E08'!$B$14),B86<>0),'E08'!$B$14/B86,0) -> 0.6609433 | E86: =IF(AND(ISNUMBER('E08'!$C$14),B86<>0),'E08'!$C$14/B86,0) -> 0.3390567 | F86: =0.5 -> 0.5 | G86: =NA() -> #N/A
A88: zf3g17 | B88: barwaterfall | C88: ="'E09'!$A$6:$B$13" -> 'E09'!$A$6:$B$13 | D88: numfmt=int;palette=padrao;gap=50;totals=0;n=7;labels=1;connectors=1
A89: Cat | B89: Src | C89: IsTotal | D89: Delta | E89: Start | F89: End | G89: Lo | H89: Hi | I89: Base | J89: PiecePos | K89: PieceNeg | L89: UpPos | M89: UpNeg | N89: DownPos | O89: DownNeg | P89: Total | Q89: LabelVal | R89: LabelPos | S89: Pos | T89: BD
A90: ='E09'!$A$7 -> Receita bruta | B90: ='E09'!$B$7 -> 129710 | C90: =IF(ISERROR(B90),FALSE,IF(ISNUMBER(B90),FALSE,OR(LOWER(TRIM(B90&""))={"e","t","=","total","subtotal"}))) -> FALSE | D90: =IF(C90,0,IF(ISNUMBER(B90),B90,0)) -> 129710 | E90: =0 -> 0 | F90: =IF($T90,_xlfn.AGGREGATE(9,6,'E09'!$B$13)-SUM($D91:$D95),$E90+$D90) -> 129710 | G90: =IF(C90,MIN(0,F90),MIN(E90,F90)) -> 0 | H90: =IF(C90,MAX(0,F90),MAX(E90,F90)) -> 129710 | I90: =MAX(0,G90)+MIN(0,H90) -> 0 | J90: =MAX(0,H90)-MAX(0,G90) -> 129710 | K90: =MIN(0,G90)-MIN(0,H90) -> 0 | L90: =IF(AND(NOT(C90),D90>=0),J90,0) -> 129710 | M90: =IF(AND(NOT(C90),D90>=0),K90,0) -> 0 | N90: =IF(AND(NOT(C90),D90<0),J90,0) -> 0 | O90: =IF(AND(NOT(C90),D90<0),K90,0) -> 0 | P90: =IF(C90,F90,0) -> 0 | Q90: =IF(C90,F90,D90) -> 129710 | R90: =IF(Q90>=0,H90,G90) -> 129710 | S90: =6.5 -> 6.5 | T90: =AND(IF(ISERROR('E09'!$B$7),FALSE,IF(ISNUMBER('E09'!$B$7),FALSE,OR(LOWER(TRIM('E09'!$B$7&""))={"e","t","=","total","subtotal"}))),COUNT('E09'!$B$13)>0,NOT(IF(ISERROR('E09'!$B$13),FALSE,IF(ISNUMBER('E09'!$B$13),FALSE,OR(LOWER(TRIM('E09'!$B$13&""))={"e","t","=","total","subtotal"}))))) -> FALSE
A91: ='E09'!$A$8 -> Custo das mercadorias | B91: ='E09'!$B$8 -> -88293 | C91: =IF(ISERROR(B91),FALSE,IF(ISNUMBER(B91),FALSE,OR(LOWER(TRIM(B91&""))={"e","t","=","total","subtotal"}))) -> FALSE | D91: =IF(C91,0,IF(ISNUMBER(B91),B91,0)) -> -88293 | E91: =F90 -> 129710 | F91: =$E91+$D91 -> 41417 | G91: =IF(C91,MIN(0,F91),MIN(E91,F91)) -> 41417 | H91: =IF(C91,MAX(0,F91),MAX(E91,F91)) -> 129710 | I91: =MAX(0,G91)+MIN(0,H91) -> 41417 | J91: =MAX(0,H91)-MAX(0,G91) -> 88293 | K91: =MIN(0,G91)-MIN(0,H91) -> 0 | L91: =IF(AND(NOT(C91),D91>=0),J91,0) -> 0 | M91: =IF(AND(NOT(C91),D91>=0),K91,0) -> 0 | N91: =IF(AND(NOT(C91),D91<0),J91,0) -> 88293 | O91: =IF(AND(NOT(C91),D91<0),K91,0) -> 0 | P91: =IF(C91,F91,0) -> 0 | Q91: =IF(C91,F91,D91) -> -88293 | R91: =IF(Q91>=0,H91,G91) -> 41417 | S91: =5.5 -> 5.5 | T91: =AND(IF(ISERROR('E09'!$B$7),FALSE,IF(ISNUMBER('E09'!$B$7),FALSE,OR(LOWER(TRIM('E09'!$B$7&""))={"e","t","=","total","subtotal"}))),COUNT('E09'!$B$13)>0,NOT(IF(ISERROR('E09'!$B$13),FALSE,IF(ISNUMBER('E09'!$B$13),FALSE,OR(LOWER(TRIM('E09'!$B$13&""))={"e","t","=","total","subtotal"}))))) -> FALSE
A92: ='E09'!$A$9 -> Despesas operacionais | B92: ='E09'!$B$9 -> -27239 | C92: =IF(ISERROR(B92),FALSE,IF(ISNUMBER(B92),FALSE,OR(LOWER(TRIM(B92&""))={"e","t","=","total","subtotal"}))) -> FALSE | D92: =IF(C92,0,IF(ISNUMBER(B92),B92,0)) -> -27239 | E92: =F91 -> 41417 | F92: =$E92+$D92 -> 14178 | G92: =IF(C92,MIN(0,F92),MIN(E92,F92)) -> 14178 | H92: =IF(C92,MAX(0,F92),MAX(E92,F92)) -> 41417 | I92: =MAX(0,G92)+MIN(0,H92) -> 14178 | J92: =MAX(0,H92)-MAX(0,G92) -> 27239 | K92: =MIN(0,G92)-MIN(0,H92) -> 0 | L92: =IF(AND(NOT(C92),D92>=0),J92,0) -> 0 | M92: =IF(AND(NOT(C92),D92>=0),K92,0) -> 0 | N92: =IF(AND(NOT(C92),D92<0),J92,0) -> 27239 | O92: =IF(AND(NOT(C92),D92<0),K92,0) -> 0 | P92: =IF(C92,F92,0) -> 0 | Q92: =IF(C92,F92,D92) -> -27239 | R92: =IF(Q92>=0,H92,G92) -> 14178 | S92: =4.5 -> 4.5 | T92: =AND(IF(ISERROR('E09'!$B$7),FALSE,IF(ISNUMBER('E09'!$B$7),FALSE,OR(LOWER(TRIM('E09'!$B$7&""))={"e","t","=","total","subtotal"}))),COUNT('E09'!$B$13)>0,NOT(IF(ISERROR('E09'!$B$13),FALSE,IF(ISNUMBER('E09'!$B$13),FALSE,OR(LOWER(TRIM('E09'!$B$13&""))={"e","t","=","total","subtotal"}))))) -> FALSE
A93: ='E09'!$A$10 -> EBITDA | B93: ='E09'!$B$10 -> e | C93: =IF(ISERROR(B93),FALSE,IF(ISNUMBER(B93),FALSE,OR(LOWER(TRIM(B93&""))={"e","t","=","total","subtotal"}))) -> TRUE | D93: =IF(C93,0,IF(ISNUMBER(B93),B93,0)) -> 0 | E93: =F92 -> 14178 | F93: =$E93+$D93 -> 14178 | G93: =IF(C93,MIN(0,F93),MIN(E93,F93)) -> 0 | H93: =IF(C93,MAX(0,F93),MAX(E93,F93)) -> 14178 | I93: =MAX(0,G93)+MIN(0,H93) -> 0 | J93: =MAX(0,H93)-MAX(0,G93) -> 14178 | K93: =MIN(0,G93)-MIN(0,H93) -> 0 | L93: =IF(AND(NOT(C93),D93>=0),J93,0) -> 0 | M93: =IF(AND(NOT(C93),D93>=0),K93,0) -> 0 | N93: =IF(AND(NOT(C93),D93<0),J93,0) -> 0 | O93: =IF(AND(NOT(C93),D93<0),K93,0) -> 0 | P93: =IF(C93,F93,0) -> 14178 | Q93: =IF(C93,F93,D93) -> 14178 | R93: =IF(Q93>=0,H93,G93) -> 14178 | S93: =3.5 -> 3.5 | T93: =AND(IF(ISERROR('E09'!$B$7),FALSE,IF(ISNUMBER('E09'!$B$7),FALSE,OR(LOWER(TRIM('E09'!$B$7&""))={"e","t","=","total","subtotal"}))),COUNT('E09'!$B$13)>0,NOT(IF(ISERROR('E09'!$B$13),FALSE,IF(ISNUMBER('E09'!$B$13),FALSE,OR(LOWER(TRIM('E09'!$B$13&""))={"e","t","=","total","subtotal"}))))) -> FALSE
A94: ='E09'!$A$11 -> Depreciação e juros | B94: ='E09'!$B$11 -> -3243 | C94: =IF(ISERROR(B94),FALSE,IF(ISNUMBER(B94),FALSE,OR(LOWER(TRIM(B94&""))={"e","t","=","total","subtotal"}))) -> FALSE | D94: =IF(C94,0,IF(ISNUMBER(B94),B94,0)) -> -3243 | E94: =F93 -> 14178 | F94: =$E94+$D94 -> 10935 | G94: =IF(C94,MIN(0,F94),MIN(E94,F94)) -> 10935 | H94: =IF(C94,MAX(0,F94),MAX(E94,F94)) -> 14178 | I94: =MAX(0,G94)+MIN(0,H94) -> 10935 | J94: =MAX(0,H94)-MAX(0,G94) -> 3243 | K94: =MIN(0,G94)-MIN(0,H94) -> 0 | L94: =IF(AND(NOT(C94),D94>=0),J94,0) -> 0 | M94: =IF(AND(NOT(C94),D94>=0),K94,0) -> 0 | N94: =IF(AND(NOT(C94),D94<0),J94,0) -> 3243 | O94: =IF(AND(NOT(C94),D94<0),K94,0) -> 0 | P94: =IF(C94,F94,0) -> 0 | Q94: =IF(C94,F94,D94) -> -3243 | R94: =IF(Q94>=0,H94,G94) -> 10935 | S94: =2.5 -> 2.5 | T94: =AND(IF(ISERROR('E09'!$B$7),FALSE,IF(ISNUMBER('E09'!$B$7),FALSE,OR(LOWER(TRIM('E09'!$B$7&""))={"e","t","=","total","subtotal"}))),COUNT('E09'!$B$13)>0,NOT(IF(ISERROR('E09'!$B$13),FALSE,IF(ISNUMBER('E09'!$B$13),FALSE,OR(LOWER(TRIM('E09'!$B$13&""))={"e","t","=","total","subtotal"}))))) -> FALSE
A95: ='E09'!$A$12 -> Impostos | B95: ='E09'!$B$12 -> -3718 | C95: =IF(ISERROR(B95),FALSE,IF(ISNUMBER(B95),FALSE,OR(LOWER(TRIM(B95&""))={"e","t","=","total","subtotal"}))) -> FALSE | D95: =IF(C95,0,IF(ISNUMBER(B95),B95,0)) -> -3718 | E95: =F94 -> 10935 | F95: =$E95+$D95 -> 7217 | G95: =IF(C95,MIN(0,F95),MIN(E95,F95)) -> 7217 | H95: =IF(C95,MAX(0,F95),MAX(E95,F95)) -> 10935 | I95: =MAX(0,G95)+MIN(0,H95) -> 7217 | J95: =MAX(0,H95)-MAX(0,G95) -> 3718 | K95: =MIN(0,G95)-MIN(0,H95) -> 0 | L95: =IF(AND(NOT(C95),D95>=0),J95,0) -> 0 | M95: =IF(AND(NOT(C95),D95>=0),K95,0) -> 0 | N95: =IF(AND(NOT(C95),D95<0),J95,0) -> 3718 | O95: =IF(AND(NOT(C95),D95<0),K95,0) -> 0 | P95: =IF(C95,F95,0) -> 0 | Q95: =IF(C95,F95,D95) -> -3718 | R95: =IF(Q95>=0,H95,G95) -> 7217 | S95: =1.5 -> 1.5 | T95: =AND(IF(ISERROR('E09'!$B$7),FALSE,IF(ISNUMBER('E09'!$B$7),FALSE,OR(LOWER(TRIM('E09'!$B$7&""))={"e","t","=","total","subtotal"}))),COUNT('E09'!$B$13)>0,NOT(IF(ISERROR('E09'!$B$13),FALSE,IF(ISNUMBER('E09'!$B$13),FALSE,OR(LOWER(TRIM('E09'!$B$13&""))={"e","t","=","total","subtotal"}))))) -> FALSE
A96: ='E09'!$A$13 -> Lucro líquido | B96: ='E09'!$B$13 -> e | C96: =OR(IF(ISERROR('E09'!$B$13),FALSE,IF(ISNUMBER('E09'!$B$13),FALSE,OR(LOWER(TRIM('E09'!$B$13&""))={"e","t","=","total","subtotal"}))),$T96) -> TRUE | D96: =IF(C96,0,IF(ISNUMBER(B96),B96,0)) -> 0 | E96: =F95 -> 7217 | F96: =IF($T96,_xlfn.AGGREGATE(9,6,'E09'!$B$13),$E96+$D96) -> 7217 | G96: =IF(C96,MIN(0,F96),MIN(E96,F96)) -> 0 | H96: =IF(C96,MAX(0,F96),MAX(E96,F96)) -> 7217 | I96: =MAX(0,G96)+MIN(0,H96) -> 0 | J96: =MAX(0,H96)-MAX(0,G96) -> 7217 | K96: =MIN(0,G96)-MIN(0,H96) -> 0 | L96: =IF(AND(NOT(C96),D96>=0),J96,0) -> 0 | M96: =IF(AND(NOT(C96),D96>=0),K96,0) -> 0 | N96: =IF(AND(NOT(C96),D96<0),J96,0) -> 0 | O96: =IF(AND(NOT(C96),D96<0),K96,0) -> 0 | P96: =IF(C96,F96,0) -> 7217 | Q96: =IF(C96,F96,D96) -> 7217 | R96: =IF(Q96>=0,H96,G96) -> 7217 | S96: =0.5 -> 0.5 | T96: =AND(IF(ISERROR('E09'!$B$7),FALSE,IF(ISNUMBER('E09'!$B$7),FALSE,OR(LOWER(TRIM('E09'!$B$7&""))={"e","t","=","total","subtotal"}))),COUNT('E09'!$B$13)>0,NOT(IF(ISERROR('E09'!$B$13),FALSE,IF(ISNUMBER('E09'!$B$13),FALSE,OR(LOWER(TRIM('E09'!$B$13&""))={"e","t","=","total","subtotal"}))))) -> FALSE
A98: 69ni49 | B98: area | C98: ="'E10'!$A$6:$D$14" -> 'E10'!$A$6:$D$14 | D98: numfmt=int;palette=padrao;n=8;legend=right;labels=1;thinlbl=3.8;totals=1;vline=1
A99: Categoria | B99: Total | C99: TotalPos | D99: Val1 | E99: Val2 | F99: Val3 | G99: Mid1 | H99: Mid2 | I99: Mid3 | J99: Pos | K99: VLine
A100: ='E10'!$A$7 -> T1/24 | B100: =_xlfn.AGGREGATE(9,6,'E10'!$B$7:$D$7) -> 17039 | C100: =IF(SUMPRODUCT(MAX(G100:I100+D100:F100/2))>0,SUMPRODUCT(MAX(G100:I100+D100:F100/2)),SUMPRODUCT(MIN(G100:I100+D100:F100/2))) -> 17039 | D100: =IF(ISNUMBER('E10'!$B$7),'E10'!$B$7,0) -> 3224 | E100: =IF(ISNUMBER('E10'!$C$7),'E10'!$C$7,0) -> 4499 | F100: =IF(ISNUMBER('E10'!$D$7),'E10'!$D$7,0) -> 9316 | G100: =SUM(D100:D100)-D100/2 -> 1612 | H100: =SUM(D100:E100)-E100/2 -> 5473.5 | I100: =SUM(D100:F100)-F100/2 -> 12381 | J100: =7.5 -> 7.5 | K100: =AVERAGE($B$100:$B$107) -> 19660.75
A101: ='E10'!$A$8 -> T2/24 | B101: =_xlfn.AGGREGATE(9,6,'E10'!$B$8:$D$8) -> 16954 | C101: =IF(SUMPRODUCT(MAX(G101:I101+D101:F101/2))>0,SUMPRODUCT(MAX(G101:I101+D101:F101/2)),SUMPRODUCT(MIN(G101:I101+D101:F101/2))) -> 16954 | D101: =IF(ISNUMBER('E10'!$B$8),'E10'!$B$8,0) -> 3217 | E101: =IF(ISNUMBER('E10'!$C$8),'E10'!$C$8,0) -> 4526 | F101: =IF(ISNUMBER('E10'!$D$8),'E10'!$D$8,0) -> 9211 | G101: =SUM(D101:D101)-D101/2 -> 1608.5 | H101: =SUM(D101:E101)-E101/2 -> 5480 | I101: =SUM(D101:F101)-F101/2 -> 12348.5 | J101: =6.5 -> 6.5 | K101: =AVERAGE($B$100:$B$107) -> 19660.75
A102: ='E10'!$A$9 -> T3/24 | B102: =_xlfn.AGGREGATE(9,6,'E10'!$B$9:$D$9) -> 19597 | C102: =IF(SUMPRODUCT(MAX(G102:I102+D102:F102/2))>0,SUMPRODUCT(MAX(G102:I102+D102:F102/2)),SUMPRODUCT(MIN(G102:I102+D102:F102/2))) -> 19597 | D102: =IF(ISNUMBER('E10'!$B$9),'E10'!$B$9,0) -> 3746 | E102: =IF(ISNUMBER('E10'!$C$9),'E10'!$C$9,0) -> 5356 | F102: =IF(ISNUMBER('E10'!$D$9),'E10'!$D$9,0) -> 10495 | G102: =SUM(D102:D102)-D102/2 -> 1873 | H102: =SUM(D102:E102)-E102/2 -> 6424 | I102: =SUM(D102:F102)-F102/2 -> 14349.5 | J102: =5.5 -> 5.5 | K102: =AVERAGE($B$100:$B$107) -> 19660.75
A103: ='E10'!$A$10 -> T4/24 | B103: =_xlfn.AGGREGATE(9,6,'E10'!$B$10:$D$10) -> 20898 | C103: =IF(SUMPRODUCT(MAX(G103:I103+D103:F103/2))>0,SUMPRODUCT(MAX(G103:I103+D103:F103/2)),SUMPRODUCT(MIN(G103:I103+D103:F103/2))) -> 20898 | D103: =IF(ISNUMBER('E10'!$B$10),'E10'!$B$10,0) -> 3943 | E103: =IF(ISNUMBER('E10'!$C$10),'E10'!$C$10,0) -> 5792 | F103: =IF(ISNUMBER('E10'!$D$10),'E10'!$D$10,0) -> 11163 | G103: =SUM(D103:D103)-D103/2 -> 1971.5 | H103: =SUM(D103:E103)-E103/2 -> 6839 | I103: =SUM(D103:F103)-F103/2 -> 15316.5 | J103: =4.5 -> 4.5 | K103: =AVERAGE($B$100:$B$107) -> 19660.75
A104: ='E10'!$A$11 -> T1/25 | B104: =_xlfn.AGGREGATE(9,6,'E10'!$B$11:$D$11) -> 18849 | C104: =IF(SUMPRODUCT(MAX(G104:I104+D104:F104/2))>0,SUMPRODUCT(MAX(G104:I104+D104:F104/2)),SUMPRODUCT(MIN(G104:I104+D104:F104/2))) -> 18849 | D104: =IF(ISNUMBER('E10'!$B$11),'E10'!$B$11,0) -> 3588 | E104: =IF(ISNUMBER('E10'!$C$11),'E10'!$C$11,0) -> 5306 | F104: =IF(ISNUMBER('E10'!$D$11),'E10'!$D$11,0) -> 9955 | G104: =SUM(D104:D104)-D104/2 -> 1794 | H104: =SUM(D104:E104)-E104/2 -> 6241 | I104: =SUM(D104:F104)-F104/2 -> 13871.5 | J104: =3.5 -> 3.5 | K104: =AVERAGE($B$100:$B$107) -> 19660.75
A105: ='E10'!$A$12 -> T2/25 | B105: =_xlfn.AGGREGATE(9,6,'E10'!$B$12:$D$12) -> 18959 | C105: =IF(SUMPRODUCT(MAX(G105:I105+D105:F105/2))>0,SUMPRODUCT(MAX(G105:I105+D105:F105/2)),SUMPRODUCT(MIN(G105:I105+D105:F105/2))) -> 18959 | D105: =IF(ISNUMBER('E10'!$B$12),'E10'!$B$12,0) -> 3538 | E105: =IF(ISNUMBER('E10'!$C$12),'E10'!$C$12,0) -> 5367 | F105: =IF(ISNUMBER('E10'!$D$12),'E10'!$D$12,0) -> 10054 | G105: =SUM(D105:D105)-D105/2 -> 1769 | H105: =SUM(D105:E105)-E105/2 -> 6221.5 | I105: =SUM(D105:F105)-F105/2 -> 13932 | J105: =2.5 -> 2.5 | K105: =AVERAGE($B$100:$B$107) -> 19660.75
A106: ='E10'!$A$13 -> T3/25 | B106: =_xlfn.AGGREGATE(9,6,'E10'!$B$13:$D$13) -> 21810 | C106: =IF(SUMPRODUCT(MAX(G106:I106+D106:F106/2))>0,SUMPRODUCT(MAX(G106:I106+D106:F106/2)),SUMPRODUCT(MIN(G106:I106+D106:F106/2))) -> 21810 | D106: =IF(ISNUMBER('E10'!$B$13),'E10'!$B$13,0) -> 4162 | E106: =IF(ISNUMBER('E10'!$C$13),'E10'!$C$13,0) -> 6298 | F106: =IF(ISNUMBER('E10'!$D$13),'E10'!$D$13,0) -> 11350 | G106: =SUM(D106:D106)-D106/2 -> 2081 | H106: =SUM(D106:E106)-E106/2 -> 7311 | I106: =SUM(D106:F106)-F106/2 -> 16135 | J106: =1.5 -> 1.5 | K106: =AVERAGE($B$100:$B$107) -> 19660.75
A107: ='E10'!$A$14 -> T4/25 | B107: =_xlfn.AGGREGATE(9,6,'E10'!$B$14:$D$14) -> 23180 | C107: =IF(SUMPRODUCT(MAX(G107:I107+D107:F107/2))>0,SUMPRODUCT(MAX(G107:I107+D107:F107/2)),SUMPRODUCT(MIN(G107:I107+D107:F107/2))) -> 23180 | D107: =IF(ISNUMBER('E10'!$B$14),'E10'!$B$14,0) -> 4415 | E107: =IF(ISNUMBER('E10'!$C$14),'E10'!$C$14,0) -> 6800 | F107: =IF(ISNUMBER('E10'!$D$14),'E10'!$D$14,0) -> 11965 | G107: =SUM(D107:D107)-D107/2 -> 2207.5 | H107: =SUM(D107:E107)-E107/2 -> 7815 | I107: =SUM(D107:F107)-F107/2 -> 17197.5 | J107: =0.5 -> 0.5 | K107: =AVERAGE($B$100:$B$107) -> 19660.75
A109: ik962d | B109: area100 | C109: ="'E11'!$A$6:$D$14" -> 'E11'!$A$6:$D$14 | D109: numfmt=int;palette=padrao;n=8;legend=right;labels=1;totals=1;ind100=1;thinlbl=
A110: Categoria | B110: Total | C110: TotalPos | D110: Val1 | E110: Val2 | F110: Val3 | G110: Mid1 | H110: Mid2 | I110: Mid3 | J110: Pos | K110: VLine
A111: ='E11'!$A$7 -> T1/24 | B111: =_xlfn.AGGREGATE(9,6,'E11'!$B$7:$D$7) -> 17039 | C111: =1 -> 1 | D111: =IF(AND(ISNUMBER('E11'!$B$7),B111<>0),'E11'!$B$7/B111,0) -> 0.18921298 | E111: =IF(AND(ISNUMBER('E11'!$C$7),B111<>0),'E11'!$C$7/B111,0) -> 0.26404132 | F111: =IF(AND(ISNUMBER('E11'!$D$7),B111<>0),'E11'!$D$7/B111,0) -> 0.5467457 | G111: =SUM(D111:D111)-D111/2 -> 0.094606491 | H111: =SUM(D111:E111)-E111/2 -> 0.32123364 | I111: =SUM(D111:F111)-F111/2 -> 0.72662715 | J111: =7.5 -> 7.5 | K111: =NA() -> #N/A
...
